Workbook

Sheet Form Responses 1
A1: Timestamp | B1: Nama Lengkap | C1: Email | D1: Nomor WhatsApp | E1: Domisili | F1: Apakah Anda Mahasiswa / Fresh Graduate | G1: Pekerjaan & Instansi Saat Ini | H1: Tools yang Ingin Dipelajari | I1: Target Join Komunitas | J1: Tau Seara Data Dari Mana? | K1: Column 1 | L1: Provinsi | M1: Cari Kerja | N1: Upskill | O1: Networking | P1: Switch Career
A2: 46049.123 | B2: Aarif Rahmaan Jalaluddin Faqiih | C2: aarifrjf@gmail.com | D2: 082242458593 | E2: Jawa Tengah | F2: Ya | G2: Mahasiswa | H2: Python, Tableau | I2: Cari Kerja, Upskill, Networking | J2: LinkedIn | K2: =IF(LEFT(D2,2)="62","0"&MID(D2,3,LEN(D2)),D2) -> 082242458593 | L2: =IFERROR( VLOOKUP( TRIM( IF(ISNUMBER(FIND(",",E2)), LEFT(E2,FIND(",",E2)-1), E2 ) ), master!A:B, 2, FALSE ), "Belum ada mapping" ) -> Jawa Tengah | M2: =IFERROR(__xludf.DUMMYFUNCTION("IF(REGEXMATCH(I2,""Cari Kerja""),1,0) "),1.0) -> 1 | N2: =IFERROR(__xludf.DUMMYFUNCTION("IF(REGEXMATCH(I2,""Upskill""),1,0) "),1.0) -> 1 | O2: =IFERROR(__xludf.DUMMYFUNCTION("IF(REGEXMATCH(I2,""Networking""),1,0) "),1.0) -> 1 | P2: =IFERROR(__xludf.DUMMYFUNCTION("IF(REGEXMATCH(I2,""Switch Career""),1,0) "),0.0) -> 0
A3: 46041.4 | B3: Abdullah Rajab Sani | C3: abdullahrsani@gmail.com | D3: 089636422658 | E3: Padang | F3: Ya | G3: belum ada | H3: Excel, SQL, Python, Power BI | I3: Cari Kerja, Upskill, Networking, Switch Career | J3: LinkedIn | K3: =IF(LEFT(D3,2)="62","0"&MID(D3,3,LEN(D3)),D3) -> 089636422658 | L3: =IFERROR( VLOOKUP( TRIM( IF(ISNUMBER(FIND(",",E3)), LEFT(E3,FIND(",",E3)-1), E3 ) ), master!A:B, 2, FALSE ), "Belum ada mapping" ) -> Sumatera Barat | M3: =IFERROR(__xludf.DUMMYFUNCTION("IF(REGEXMATCH(I3,""Cari Kerja""),1,0) "),1.0) -> 1 | N3: =IFERROR(__xludf.DUMMYFUNCTION("IF(REGEXMATCH(I3,""Upskill""),1,0) "),1.0) -> 1 | O3: =IFERROR(__xludf.DUMMYFUNCTION("IF(REGEXMATCH(I3,""Networking""),1,0) "),1.0) -> 1 | P3: =IFERROR(__xludf.DUMMYFUNCTION("IF(REGEXMATCH(I3,""Switch Career""),1,0) "),1.0) -> 1
A4: 46159.859 | B4: Abdur Rochman | C4: abdurrochman195@gmail.com | D4: 085785757834 | E4: Surabaya | F4: Ya | G4: Freelance Web Development | H4: Excel, SQL, Python, Power BI, Databases | I4: Cari Kerja, Upskill, Networking | J4: Teman | K4: =IF(LEFT(D4,2)="62","0"&MID(D4,3,LEN(D4)),D4) -> 085785757834 | L4: =IFERROR( VLOOKUP( TRIM( IF(ISNUMBER(FIND(",",E4)), LEFT(E4,FIND(",",E4)-1), E4 ) ), master!A:B, 2, FALSE ), "Belum ada mapping" ) -> Jawa Timur | M4: =IFERROR(__xludf.DUMMYFUNCTION("IF(REGEXMATCH(I4,""Cari Kerja""),1,0) "),1.0) -> 1 | N4: =IFERROR(__xludf.DUMMYFUNCTION("IF(REGEXMATCH(I4,""Upskill""),1,0) "),1.0) -> 1 | O4: =IFERROR(__xludf.DUMMYFUNCTION("IF(REGEXMATCH(I4,""Networking""),1,0) "),1.0) -> 1 | P4: =IFERROR(__xludf.DUMMYFUNCTION("IF(REGEXMATCH(I4,""Switch Career""),1,0) "),0.0) -> 0
A5: 46043.57 | B5: Abdurrahman Qeis Ahmad | C5: qeisahmad98@gmail.com | D5: 0895421552311 | E5: Bandung | F5: Ya | G5: Konsultan Perencanaan Kota | H5: Python, Power BI | I5: Upskill | J5: LinkedIn | K5: =IF(LEFT(D5,2)="62","0"&MID(D5,3,LEN(D5)),D5) -> 0895421552311 | L5: =IFERROR( VLOOKUP( TRIM( IF(ISNUMBER(FIND(",",E5)), LEFT(E5,FIND(",",E5)-1), E5 ) ), master!A:B, 2, FALSE ), "Belum ada mapping" ) -> Jawa Barat | M5: =IFERROR(__xludf.DUMMYFUNCTION("IF(REGEXMATCH(I5,""Cari Kerja""),1,0) "),0.0) -> 0 | N5: =IFERROR(__xludf.DUMMYFUNCTION("IF(REGEXMATCH(I5,""Upskill""),1,0) "),1.0) -> 1 | O5: =IFERROR(__xludf.DUMMYFUNCTION("IF(REGEXMATCH(I5,""Networking""),1,0) "),0.0) -> 0 | P5: =IFERROR(__xludf.DUMMYFUNCTION("IF(REGEXMATCH(I5,""Switch Career""),1,0) "),0.0) -> 0
A6: 46043.298 | B6: Abid Maulana Akbar | C6: abidma012@gmail.com | D6: 085803655302 | E6: Yogyakarta | F6: Tidak | G6: Senior Barista _- Esha kopi | H6: Excel, SQL, Python, Power BI, Looker Studio, Databases, Tableau | I6: Upskill, Networking, Switch Career | J6: Teman | K6: =IF(LEFT(D6,2)="62","0"&MID(D6,3,LEN(D6)),D6) -> 085803655302 | L6: =IFERROR( VLOOKUP( TRIM( IF(ISNUMBER(FIND(",",E6)), LEFT(E6,FIND(",",E6)-1), E6 ) ), master!A:B, 2, FALSE ), "Belum ada mapping" ) -> DI Yogyakarta | M6: =IFERROR(__xludf.DUMMYFUNCTION("IF(REGEXMATCH(I6,""Cari Kerja""),1,0) "),0.0) -> 0 | N6: =IFERROR(__xludf.DUMMYFUNCTION("IF(REGEXMATCH(I6,""Upskill""),1,0) "),1.0) -> 1 | O6: =IFERROR(__xludf.DUMMYFUNCTION("IF(REGEXMATCH(I6,""Networking""),1,0) "),1.0) -> 1 | P6: =IFERROR(__xludf.DUMMYFUNCTION("IF(REGEXMATCH(I6,""Switch Career""),1,0) "),1.0) -> 1
A7: 46040.433 | B7: Abimanyu Priyatno | C7: abimanyupri@gmail.com | D7: 085692331114 | E7: Tangerang | F7: Ya | G7: Data & Informasi System Staff, Kementerian Desa PDT | H7: Excel, SQL, Power BI, Tableau | I7: Upskill, Networking | J7: Teman | K7: =IF(LEFT(D7,2)="62","0"&MID(D7,3,LEN(D7)),D7) -> 085692331114 | L7: =IFERROR( VLOOKUP( TRIM( IF(ISNUMBER(FIND(",",E7)), LEFT(E7,FIND(",",E7)-1), E7 ) ), master!A:B, 2, FALSE ), "Belum ada mapping" ) -> Banten | M7: =IFERROR(__xludf.DUMMYFUNCTION("IF(REGEXMATCH(I7,""Cari Kerja""),1,0) "),0.0) -> 0 | N7: =IFERROR(__xludf.DUMMYFUNCTION("IF(REGEXMATCH(I7,""Upskill""),1,0) "),1.0) -> 1 | O7: =IFERROR(__xludf.DUMMYFUNCTION("IF(REGEXMATCH(I7,""Networking""),1,0) "),1.0) -> 1 | P7: =IFERROR(__xludf.DUMMYFUNCTION("IF(REGEXMATCH(I7,""Switch Career""),1,0) "),0.0) -> 0
A8: 46045.478 | B8: Achmad Chilmi Syifa | C8: hylmisyifa@gmail.com | D8: 083843588880 | E8: Kudus | F8: Tidak | G8: Admin Personalia | H8: Excel, SQL, Python, Power BI, Looker Studio, Databases, Tableau | I8: Cari Kerja, Upskill, Networking, Switch Career | J8: LinkedIn | K8: =IF(LEFT(D8,2)="62","0"&MID(D8,3,LEN(D8)),D8) -> 083843588880 | L8: =IFERROR( VLOOKUP( TRIM( IF(ISNUMBER(FIND(",",E8)), LEFT(E8,FIND(",",E8)-1), E8 ) ), master!A:B, 2, FALSE ), "Belum ada mapping" ) -> Jawa Tengah | M8: =IFERROR(__xludf.DUMMYFUNCTION("IF(REGEXMATCH(I8,""Cari Kerja""),1,0) "),1.0) -> 1 | N8: =IFERROR(__xludf.DUMMYFUNCTION("IF(REGEXMATCH(I8,""Upskill""),1,0) "),1.0) -> 1 | O8: =IFERROR(__xludf.DUMMYFUNCTION("IF(REGEXMATCH(I8,""Networking""),1,0) "),1.0) -> 1 | P8: =IFERROR(__xludf.DUMMYFUNCTION("IF(REGEXMATCH(I8,""Switch Career""),1,0) "),1.0) -> 1
A9: 46041.399 | B9: Achmad jamaah firdaus | C9: Achmadjamaahfirdaus0099@gmail.com | D9: 083865555032 | E9: Boyolali | F9: Ya | G9: - | H9: Excel, SQL, Python, Power BI, Looker Studio, Databases, Airflow | I9: Cari Kerja, Upskill, Networking | J9: LinkedIn | K9: =IF(LEFT(D9,2)="62","0"&MID(D9,3,LEN(D9)),D9) -> 083865555032 | L9: =IFERROR( VLOOKUP( TRIM( IF(ISNUMBER(FIND(",",E9)), LEFT(E9,FIND(",",E9)-1), E9 ) ), master!A:B, 2, FALSE ), "Belum ada mapping" ) -> Jawa Tengah | M9: =IFERROR(__xludf.DUMMYFUNCTION("IF(REGEXMATCH(I9,""Cari Kerja""),1,0) "),1.0) -> 1 | N9: =IFERROR(__xludf.DUMMYFUNCTION("IF(REGEXMATCH(I9,""Upskill""),1,0) "),1.0) -> 1 | O9: =IFERROR(__xludf.DUMMYFUNCTION("IF(REGEXMATCH(I9,""Networking""),1,0) "),1.0) -> 1 | P9: =IFERROR(__xludf.DUMMYFUNCTION("IF(REGEXMATCH(I9,""Switch Career""),1,0) "),0.0) -> 0
A10: 46045.612 | B10: Achmad Kurniansyah | C10: achmadkurniansyahthalib@gmail.com | D10: 087814074676 | E10: Tangerang | F10: Tidak | G10: Senior Business Intelegence Dekoruma | H10: Excel, SQL, Python, Power BI, Looker Studio, Databases, Tableau | I10: Upskill, Networking | J10: Instagram | K10: =IF(LEFT(D10,2)="62","0"&MID(D10,3,LEN(D10)),D10) -> 087814074676 | L10: =IFERROR( VLOOKUP( TRIM( IF(ISNUMBER(FIND(",",E10)), LEFT(E10,FIND(",",E10)-1), E10 ) ), master!A:B, 2, FALSE ), "Belum ada mapping" ) -> Banten | M10: =IFERROR(__xludf.DUMMYFUNCTION("IF(REGEXMATCH(I10,""Cari Kerja""),1,0) "),0.0) -> 0 | N10: =IFERROR(__xludf.DUMMYFUNCTION("IF(REGEXMATCH(I10,""Upskill""),1,0) "),1.0) -> 1 | O10: =IFERROR(__xludf.DUMMYFUNCTION("IF(REGEXMATCH(I10,""Networking""),1,0) "),1.0) -> 1 | P10: =IFERROR(__xludf.DUMMYFUNCTION("IF(REGEXMATCH(I10,""Switch Career""),1,0) "),0.0) -> 0
A11: 46045.711 | B11: Addo Adantya Abiesa | C11: abiesa.addo@gmail.com | D11: 087776964621 | E11: Sidoarjo, Jawa Timur | F11: Tidak | G11: Audit - PT Jawa Berkat Indonesia | H11: Excel, SQL, Python, Power BI, Looker Studio, Tableau | I11: Cari Kerja, Upskill, Networking, Switch Career | J11: Teman | K11: =IF(LEFT(D11,2)="62","0"&MID(D11,3,LEN(D11)),D11) -> 087776964621 | L11: =IFERROR( VLOOKUP( TRIM( IF(ISNUMBER(FIND(",",E11)), LEFT(E11,FIND(",",E11)-1), E11 ) ), master!A:B, 2, FALSE ), "Belum ada mapping" ) -> Jawa Timur | M11: =IFERROR(__xludf.DUMMYFUNCTION("IF(REGEXMATCH(I11,""Cari Kerja""),1,0) "),1.0) -> 1 | N11: =IFERROR(__xludf.DUMMYFUNCTION("IF(REGEXMATCH(I11,""Upskill""),1,0) "),1.0) -> 1 | O11: =IFERROR(__xludf.DUMMYFUNCTION("IF(REGEXMATCH(I11,""Networking""),1,0) "),1.0) -> 1 | P11: =IFERROR(__xludf.DUMMYFUNCTION("IF(REGEXMATCH(I11,""Switch Career""),1,0) "),1.0) -> 1
A12: 46134.695 | B12: Ade Krisna | C12: adekrisnasubagyo18@gmail.com | D12: 082228461957 | E12: Banyumas | F12: Ya | G12: - | H12: Excel, SQL, Python, Power BI, Looker Studio, Databases | I12: Cari Kerja | J12: Instagram | K12: =IF(LEFT(D12,2)="62","0"&MID(D12,3,LEN(D12)),D12) -> 082228461957 | L12: =IFERROR( VLOOKUP( TRIM( IF(ISNUMBER(FIND(",",E12)), LEFT(E12,FIND(",",E12)-1), E12 ) ), master!A:B, 2, FALSE ), "Belum ada mapping" ) -> Jawa Tengah | M12: =IFERROR(__xludf.DUMMYFUNCTION("IF(REGEXMATCH(I12,""Cari Kerja""),1,0) "),1.0) -> 1 | N12: =IFERROR(__xludf.DUMMYFUNCTION("IF(REGEXMATCH(I12,""Upskill""),1,0) "),0.0) -> 0 | O12: =IFERROR(__xludf.DUMMYFUNCTION("IF(REGEXMATCH(I12,""Networking""),1,0) "),0.0) -> 0 | P12: =IFERROR(__xludf.DUMMYFUNCTION("IF(REGEXMATCH(I12,""Switch Career""),1,0) "),0.0) -> 0
A13: 46046.568 | B13: Ade Krisna Subagyo | C13: adekrisnasubagyo18@gmail.com | D13: 082228461957 | E13: Jawa Tengah | F13: Ya | G13: - | H13: Excel, SQL, Python, Power BI, Looker Studio, Databases, Tableau | I13: Cari Kerja, Upskill, Networking | J13: LinkedIn | K13: =IF(LEFT(D13,2)="62","0"&MID(D13,3,LEN(D13)),D13) -> 082228461957 | L13: =IFERROR( VLOOKUP( TRIM( IF(ISNUMBER(FIND(",",E13)), LEFT(E13,FIND(",",E13)-1), E13 ) ), master!A:B, 2, FALSE ), "Belum ada mapping" ) -> Jawa Tengah | M13: =IFERROR(__xludf.DUMMYFUNCTION("IF(REGEXMATCH(I13,""Cari Kerja""),1,0) "),1.0) -> 1 | N13: =IFERROR(__xludf.DUMMYFUNCTION("IF(REGEXMATCH(I13,""Upskill""),1,0) "),1.0) -> 1 | O13: =IFERROR(__xludf.DUMMYFUNCTION("IF(REGEXMATCH(I13,""Networking""),1,0) "),1.0) -> 1 | P13: =IFERROR(__xludf.DUMMYFUNCTION("IF(REGEXMATCH(I13,""Switch Career""),1,0) "),0.0) -> 0
A14: 46046.415 | B14: Ade Mutia | C14: ademutia.suwardi@gmail.com | D14: 085862612541 | E14: Bekasi | F14: Ya | G14: - | H14: Excel, SQL, Python, Power BI, Tableau | I14: Upskill | J14: Teman | K14: =IF(LEFT(D14,2)="62","0"&MID(D14,3,LEN(D14)),D14) -> 085862612541 | L14: =IFERROR( VLOOKUP( TRIM( IF(ISNUMBER(FIND(",",E14)), LEFT(E14,FIND(",",E14)-1), E14 ) ), master!A:B, 2, FALSE ), "Belum ada mapping" ) -> Jawa Barat | M14: =IFERROR(__xludf.DUMMYFUNCTION("IF(REGEXMATCH(I14,""Cari Kerja""),1,0) "),0.0) -> 0 | N14: =IFERROR(__xludf.DUMMYFUNCTION("IF(REGEXMATCH(I14,""Upskill""),1,0) "),1.0) -> 1 | O14: =IFERROR(__xludf.DUMMYFUNCTION("IF(REGEXMATCH(I14,""Networking""),1,0) "),0.0) -> 0 | P14: =IFERROR(__xludf.DUMMYFUNCTION("IF(REGEXMATCH(I14,""Switch Career""),1,0) "),0.0) -> 0
A15: 46045.807 | B15: Ade Tri Oktavian | C15: adetrioktavian12@gmail.com | D15: 081380305890 | E15: Jakarta Timur | F15: Tidak | G15: Warehouse - Supply Chain | H15: Excel, SQL, Python, Power BI | I15: Upskill, Networking | J15: LinkedIn | K15: =IF(LEFT(D15,2)="62","0"&MID(D15,3,LEN(D15)),D15) -> 081380305890 | L15: =IFERROR( VLOOKUP( TRIM( IF(ISNUMBER(FIND(",",E15)), LEFT(E15,FIND(",",E15)-1), E15 ) ), master!A:B, 2, FALSE ), "Belum ada mapping" ) -> Jakarta | M15: =IFERROR(__xludf.DUMMYFUNCTION("IF(REGEXMATCH(I15,""Cari Kerja""),1,0) "),0.0) -> 0 | N15: =IFERROR(__xludf.DUMMYFUNCTION("IF(REGEXMATCH(I15,""Upskill""),1,0) "),1.0) -> 1 | O15: =IFERROR(__xludf.DUMMYFUNCTION("IF(REGEXMATCH(I15,""Networking""),1,0) "),1.0) -> 1 | P15: =IFERROR(__xludf.DUMMYFUNCTION("IF(REGEXMATCH(I15,""Switch Career""),1,0) "),0.0) -> 0
A16: 46047.994 | B16: Adek Putri | C16: adek19putri@gmail.com | D16: 08116681815 | E16: Padang | F16: Tidak | G16: ASN | H16: Excel, SQL, Python, Power BI, Looker Studio, Databases, Tableau, Anything | I16: Cari Kerja, Upskill, Networking, Switch Career | J16: LinkedIn | K16: =IF(LEFT(D16,2)="62","0"&MID(D16,3,LEN(D16)),D16) -> 08116681815 | L16: =IFERROR( VLOOKUP( TRIM( IF(ISNUMBER(FIND(",",E16)), LEFT(E16,FIND(",",E16)-1), E16 ) ), master!A:B, 2, FALSE ), "Belum ada mapping" ) -> Sumatera Barat | M16: =IFERROR(__xludf.DUMMYFUNCTION("IF(REGEXMATCH(I16,""Cari Kerja""),1,0) "),1.0) -> 1 | N16: =IFERROR(__xludf.DUMMYFUNCTION("IF(REGEXMATCH(I16,""Upskill""),1,0) "),1.0) -> 1 | O16: =IFERROR(__xludf.DUMMYFUNCTION("IF(REGEXMATCH(I16,""Networking""),1,0) "),1.0) -> 1 | P16: =IFERROR(__xludf.DUMMYFUNCTION("IF(REGEXMATCH(I16,""Switch Career""),1,0) "),1.0) -> 1
A17: 46042.408 | B17: Adhyatnika Nugraha | C17: adhyatnika.nugraha@gmail.com | D17: 081803539087 | E17: Cianjur | F17: Tidak | G17: Staff HR di salah satu Bank Swasta | H17: Excel, SQL, Python, Power BI, Databases | I17: Cari Kerja, Networking | J17: Teman | K17: =IF(LEFT(D17,2)="62","0"&MID(D17,3,LEN(D17)),D17) -> 081803539087 | L17: =IFERROR( VLOOKUP( TRIM( IF(ISNUMBER(FIND(",",E17)), LEFT(E17,FIND(",",E17)-1), E17 ) ), master!A:B, 2, FALSE ), "Belum ada mapping" ) -> Jawa Barat | M17: =IFERROR(__xludf.DUMMYFUNCTION("IF(REGEXMATCH(I17,""Cari Kerja""),1,0) "),1.0) -> 1 | N17: =IFERROR(__xludf.DUMMYFUNCTION("IF(REGEXMATCH(I17,""Upskill""),1,0) "),0.0) -> 0 | O17: =IFERROR(__xludf.DUMMYFUNCTION("IF(REGEXMATCH(I17,""Networking""),1,0) "),1.0) -> 1 | P17: =IFERROR(__xludf.DUMMYFUNCTION("IF(REGEXMATCH(I17,""Switch Career""),1,0) "),0.0) -> 0
A18: 46040.506 | B18: Adi Syah Putra Simbolon | C18: adisyahsimbolon@gamil.con | D18: 085372235592 | E18: Medan | F18: Tidak | G18: Idle | H18: Excel, SQL, Python, Power BI, Looker Studio, Databases, Tableau | I18: Cari Kerja, Upskill, Networking, Switch Career | J18: LinkedIn | K18: =IF(LEFT(D18,2)="62","0"&MID(D18,3,LEN(D18)),D18) -> 085372235592 | L18: =IFERROR( VLOOKUP( TRIM( IF(ISNUMBER(FIND(",",E18)), LEFT(E18,FIND(",",E18)-1), E18 ) ), master!A:B, 2, FALSE ), "Belum ada mapping" ) -> Sumatera Utara | M18: =IFERROR(__xludf.DUMMYFUNCTION("IF(REGEXMATCH(I18,""Cari Kerja""),1,0) "),1.0) -> 1 | N18: =IFERROR(__xludf.DUMMYFUNCTION("IF(REGEXMATCH(I18,""Upskill""),1,0) "),1.0) -> 1 | O18: =IFERROR(__xludf.DUMMYFUNCTION("IF(REGEXMATCH(I18,""Networking""),1,0) "),1.0) -> 1 | P18: =IFERROR(__xludf.DUMMYFUNCTION("IF(REGEXMATCH(I18,""Switch Career""),1,0) "),1.0) -> 1
A19: 46042.531 | B19: Adinda Dwi Nur Rahmawati | C19: dadinda868@gmail.com | D19: 088989430679 | E19: Gresik | F19: Ya | G19: Mahasiswa | H19: Excel, SQL, Python, Power BI, Tableau | I19: Cari Kerja, Upskill, Networking | J19: LinkedIn | K19: =IF(LEFT(D19,2)="62","0"&MID(D19,3,LEN(D19)),D19) -> 088989430679 | L19: =IFERROR( VLOOKUP( TRIM( IF(ISNUMBER(FIND(",",E19)), LEFT(E19,FIND(",",E19)-1), E19 ) ), master!A:B, 2, FALSE ), "Belum ada mapping" ) -> Jawa Timur | M19: =IFERROR(__xludf.DUMMYFUNCTION("IF(REGEXMATCH(I19,""Cari Kerja""),1,0) "),1.0) -> 1 | N19: =IFERROR(__xludf.DUMMYFUNCTION("IF(REGEXMATCH(I19,""Upskill""),1,0) "),1.0) -> 1 | O19: =IFERROR(__xludf.DUMMYFUNCTION("IF(REGEXMATCH(I19,""Networking""),1,0) "),1.0) -> 1 | P19: =IFERROR(__xludf.DUMMYFUNCTION("IF(REGEXMATCH(I19,""Switch Career""),1,0) "),0.0) -> 0
A20: 46043.383 | B20: Adinda Dwi Putri | C20: dindaadwptri@gmail.com | D20: 085256392566 | E20: Makassar | F20: Ya | G20: Quality System Intern | H20: Excel, SQL, Python, Power BI, Looker Studio, Databases, Tableau | I20: Cari Kerja, Upskill, Networking | J20: LinkedIn | K20: =IF(LEFT(D20,2)="62","0"&MID(D20,3,LEN(D20)),D20) -> 085256392566 | L20: =IFERROR( VLOOKUP( TRIM( IF(ISNUMBER(FIND(",",E20)), LEFT(E20,FIND(",",E20)-1), E20 ) ), master!A:B, 2, FALSE ), "Belum ada mapping" ) -> Sulawesi Selatan | M20: =IFERROR(__xludf.DUMMYFUNCTION("IF(REGEXMATCH(I20,""Cari Kerja""),1,0) "),1.0) -> 1 | N20: =IFERROR(__xludf.DUMMYFUNCTION("IF(REGEXMATCH(I20,""Upskill""),1,0) "),1.0) -> 1 | O20: =IFERROR(__xludf.DUMMYFUNCTION("IF(REGEXMATCH(I20,""Networking""),1,0) "),1.0) -> 1 | P20: =IFERROR(__xludf.DUMMYFUNCTION("IF(REGEXMATCH(I20,""Switch Career""),1,0) "),0.0) -> 0
A21: 46042.292 | B21: Adinda Putri Satya | C21: putrisd188@gmail.com | D21: 081221196013 | E21: Jawa Barat, | F21: Ya | G21: Freshgraduated | H21: Excel, SQL, Power BI, Looker Studio | I21: Cari Kerja, Upskill | J21: LinkedIn | K21: =IF(LEFT(D21,2)="62","0"&MID(D21,3,LEN(D21)),D21) -> 081221196013 | L21: =IFERROR( VLOOKUP( TRIM( IF(ISNUMBER(FIND(",",E21)), LEFT(E21,FIND(",",E21)-1), E21 ) ), master!A:B, 2, FALSE ), "Belum ada mapping" ) -> Jawa Barat | M21: =IFERROR(__xludf.DUMMYFUNCTION("IF(REGEXMATCH(I21,""Cari Kerja""),1,0) "),1.0) -> 1 | N21: =IFERROR(__xludf.DUMMYFUNCTION("IF(REGEXMATCH(I21,""Upskill""),1,0) "),1.0) -> 1 | O21: =IFERROR(__xludf.DUMMYFUNCTION("IF(REGEXMATCH(I21,""Networking""),1,0) "),0.0) -> 0 | P21: =IFERROR(__xludf.DUMMYFUNCTION("IF(REGEXMATCH(I21,""Switch Career""),1,0) "),0.0) -> 0
A22: 46046.61 | B22: Adinda Rahma Illawati | C22: rdinda659@gmail.com | D22: 089524739800 | E22: Bandung | F22: Ya | G22: Magang - Pemerintahan (BBPMP Jabar) | H22: Power BI, Looker Studio, Tableau | I22: Cari Kerja, Upskill | J22: LinkedIn | K22: =IF(LEFT(D22,2)="62","0"&MID(D22,3,LEN(D22)),D22) -> 089524739800 | L22: =IFERROR( VLOOKUP( TRIM( IF(ISNUMBER(FIND(",",E22)), LEFT(E22,FIND(",",E22)-1), E22 ) ), master!A:B, 2, FALSE ), "Belum ada mapping" ) -> Jawa Barat | M22: =IFERROR(__xludf.DUMMYFUNCTION("IF(REGEXMATCH(I22,""Cari Kerja""),1,0) "),1.0) -> 1 | N22: =IFERROR(__xludf.DUMMYFUNCTION("IF(REGEXMATCH(I22,""Upskill""),1,0) "),1.0) -> 1 | O22: =IFERROR(__xludf.DUMMYFUNCTION("IF(REGEXMATCH(I22,""Networking""),1,0) "),0.0) -> 0 | P22: =IFERROR(__xludf.DUMMYFUNCTION("IF(REGEXMATCH(I22,""Switch Career""),1,0) "),0.0) -> 0
A23: 46040.487 | B23: Aditya Rizky Widiarta | C23: adityawidiarta0@gmail.com | D23: 08119255511 | E23: Bekasi | F23: Tidak | G23: PT SOKKA TAMA FIBER | H23: Excel, SQL, Python, Power BI, Looker Studio, Databases, Tableau | I23: Upskill, Networking, Switch Career | J23: Instagram | K23: =IF(LEFT(D23,2)="62","0"&MID(D23,3,LEN(D23)),D23) -> 08119255511 | L23: =IFERROR( VLOOKUP( TRIM( IF(ISNUMBER(FIND(",",E23)), LEFT(E23,FIND(",",E23)-1), E23 ) ), master!A:B, 2, FALSE ), "Belum ada mapping" ) -> Jawa Barat | M23: =IFERROR(__xludf.DUMMYFUNCTION("IF(REGEXMATCH(I23,""Cari Kerja""),1,0) "),0.0) -> 0 | N23: =IFERROR(__xludf.DUMMYFUNCTION("IF(REGEXMATCH(I23,""Upskill""),1,0) "),1.0) -> 1 | O23: =IFERROR(__xludf.DUMMYFUNCTION("IF(REGEXMATCH(I23,""Networking""),1,0) "),1.0) -> 1 | P23: =IFERROR(__xludf.DUMMYFUNCTION("IF(REGEXMATCH(I23,""Switch Career""),1,0) "),1.0) -> 1
A24: 46042.517 | B24: Adrian Taufan | C24: adriantaufan3129@gmail.com | D24: 081356910981 | E24: Tangerang | F24: Ya | G24: Student | H24: Excel, SQL, Python, Power BI, Looker Studio, Databases, Tableau | I24: Upskill, Networking | J24: LinkedIn | K24: =IF(LEFT(D24,2)="62","0"&MID(D24,3,LEN(D24)),D24) -> 081356910981 | L24: =IFERROR( VLOOKUP( TRIM( IF(ISNUMBER(FIND(",",E24)), LEFT(E24,FIND(",",E24)-1), E24 ) ), master!A:B, 2, FALSE ), "Belum ada mapping" ) -> Banten | M24: =IFERROR(__xludf.DUMMYFUNCTION("IF(REGEXMATCH(I24,""Cari Kerja""),1,0) "),0.0) -> 0 | N24: =IFERROR(__xludf.DUMMYFUNCTION("IF(REGEXMATCH(I24,""Upskill""),1,0) "),1.0) -> 1 | O24: =IFERROR(__xludf.DUMMYFUNCTION("IF(REGEXMATCH(I24,""Networking""),1,0) "),1.0) -> 1 | P24: =IFERROR(__xludf.DUMMYFUNCTION("IF(REGEXMATCH(I24,""Switch Career""),1,0) "),0.0) -> 0
A25: 46040.496 | B25: Afdhal Wirahadi | C25: afdhal.wirahadi@gmail.com | D25: 081316016661 | E25: Dumai | F25: Tidak | G25: Freelance | H25: Excel, SQL, Python, Power BI, Tableau | I25: Upskill | J25: LinkedIn | K25: =IF(LEFT(D25,2)="62","0"&MID(D25,3,LEN(D25)),D25) -> 081316016661 | L25: =IFERROR( VLOOKUP( TRIM( IF(ISNUMBER(FIND(",",E25)), LEFT(E25,FIND(",",E25)-1), E25 ) ), master!A:B, 2, FALSE ), "Belum ada mapping" ) -> Riau | M25: =IFERROR(__xludf.DUMMYFUNCTION("IF(REGEXMATCH(I25,""Cari Kerja""),1,0) "),0.0) -> 0 | N25: =IFERROR(__xludf.DUMMYFUNCTION("IF(REGEXMATCH(I25,""Upskill""),1,0) "),1.0) -> 1 | O25: =IFERROR(__xludf.DUMMYFUNCTION("IF(REGEXMATCH(I25,""Networking""),1,0) "),0.0) -> 0 | P25: =IFERROR(__xludf.DUMMYFUNCTION("IF(REGEXMATCH(I25,""Switch Career""),1,0) "),0.0) -> 0
A26: 46046.348 | B26: Afdhal Wirahadi | C26: afdhal.wirahadi@gmail.com | D26: 081316016661 | E26: Dumai | F26: Tidak | G26: Freelance | H26: Excel, SQL, Python, Power BI, Tableau | I26: Upskill | J26: LinkedIn | K26: =IF(LEFT(D26,2)="62","0"&MID(D26,3,LEN(D26)),D26) -> 081316016661 | L26: =IFERROR( VLOOKUP( TRIM( IF(ISNUMBER(FIND(",",E26)), LEFT(E26,FIND(",",E26)-1), E26 ) ), master!A:B, 2, FALSE ), "Belum ada mapping" ) -> Riau | M26: =IFERROR(__xludf.DUMMYFUNCTION("IF(REGEXMATCH(I26,""Cari Kerja""),1,0) "),0.0) -> 0 | N26: =IFERROR(__xludf.DUMMYFUNCTION("IF(REGEXMATCH(I26,""Upskill""),1,0) "),1.0) -> 1 | O26: =IFERROR(__xludf.DUMMYFUNCTION("IF(REGEXMATCH(I26,""Networking""),1,0) "),0.0) -> 0 | P26: =IFERROR(__xludf.DUMMYFUNCTION("IF(REGEXMATCH(I26,""Switch Career""),1,0) "),0.0) -> 0
A27: 46122.541 | B27: Afdhal Wirahadi | C27: afdhal.wirahadi@gmail.com | D27: 081316016661 | E27: Pekanbaru | F27: Tidak | G27: Un employee | H27: Excel, Python, Power BI | I27: Upskill, Switch Career | J27: LinkedIn | K27: =IF(LEFT(D27,2)="62","0"&MID(D27,3,LEN(D27)),D27) -> 081316016661 | L27: =IFERROR( VLOOKUP( TRIM( IF(ISNUMBER(FIND(",",E27)), LEFT(E27,FIND(",",E27)-1), E27 ) ), master!A:B, 2, FALSE ), "Belum ada mapping" ) -> Riau | M27: =IFERROR(__xludf.DUMMYFUNCTION("IF(REGEXMATCH(I27,""Cari Kerja""),1,0) "),0.0) -> 0 | N27: =IFERROR(__xludf.DUMMYFUNCTION("IF(REGEXMATCH(I27,""Upskill""),1,0) "),1.0) -> 1 | O27: =IFERROR(__xludf.DUMMYFUNCTION("IF(REGEXMATCH(I27,""Networking""),1,0) "),0.0) -> 0 | P27: =IFERROR(__xludf.DUMMYFUNCTION("IF(REGEXMATCH(I27,""Switch Career""),1,0) "),1.0) -> 1
A28: 46040.421 | B28: Afifa Zahia Prananto | C28: afifa020204@gmail.com | D28: 0881025319045 | E28: Depok | F28: Ya | G28: Politeknik Negeri Jakarta | H28: Excel, SQL, Python, Power BI, Looker Studio | I28: Cari Kerja, Upskill, Networking, Switch Career | J28: LinkedIn | K28: =IF(LEFT(D28,2)="62","0"&MID(D28,3,LEN(D28)),D28) -> 0881025319045 | L28: =IFERROR( VLOOKUP( TRIM( IF(ISNUMBER(FIND(",",E28)), LEFT(E28,FIND(",",E28)-1), E28 ) ), master!A:B, 2, FALSE ), "Belum ada mapping" ) -> Jawa Barat | M28: =IFERROR(__xludf.DUMMYFUNCTION("IF(REGEXMATCH(I28,""Cari Kerja""),1,0) "),1.0) -> 1 | N28: =IFERROR(__xludf.DUMMYFUNCTION("IF(REGEXMATCH(I28,""Upskill""),1,0) "),1.0) -> 1 | O28: =IFERROR(__xludf.DUMMYFUNCTION("IF(REGEXMATCH(I28,""Networking""),1,0) "),1.0) -> 1 | P28: =IFERROR(__xludf.DUMMYFUNCTION("IF(REGEXMATCH(I28,""Switch Career""),1,0) "),1.0) -> 1
A29: 46043.961 | B29: Agam Gunawan Setiaji | C29: agasawork@gmail.com | D29: 085641737295 | E29: Purworejo | F29: Ya | G29: - | H29: Excel, SQL, Python, Looker Studio | I29: Cari Kerja, Upskill, Networking | J29: LinkedIn | K29: =IF(LEFT(D29,2)="62","0"&MID(D29,3,LEN(D29)),D29) -> 085641737295 | L29: =IFERROR( VLOOKUP( TRIM( IF(ISNUMBER(FIND(",",E29)), LEFT(E29,FIND(",",E29)-1), E29 ) ), master!A:B, 2, FALSE ), "Belum ada mapping" ) -> Jawa Tengah | M29: =IFERROR(__xludf.DUMMYFUNCTION("IF(REGEXMATCH(I29,""Cari Kerja""),1,0) "),1.0) -> 1 | N29: =IFERROR(__xludf.DUMMYFUNCTION("IF(REGEXMATCH(I29,""Upskill""),1,0) "),1.0) -> 1 | O29: =IFERROR(__xludf.DUMMYFUNCTION("IF(REGEXMATCH(I29,""Networking""),1,0) "),1.0) -> 1 | P29: =IFERROR(__xludf.DUMMYFUNCTION("IF(REGEXMATCH(I29,""Switch Career""),1,0) "),0.0) -> 0
A30: 46045.845 | B30: Agatha Anggriani Tumanggor | C30: agathatumanggor07@gmail.com | D30: 082184471311 | E30: Medan | F30: Ya | G30: Tidak ada | H30: SQL, Python, Power BI, Looker Studio, Tableau | I30: Cari Kerja | J30: LinkedIn | K30: =IF(LEFT(D30,2)="62","0"&MID(D30,3,LEN(D30)),D30) -> 082184471311 | L30: =IFERROR( VLOOKUP( TRIM( IF(ISNUMBER(FIND(",",E30)), LEFT(E30,FIND(",",E30)-1), E30 ) ), master!A:B, 2, FALSE ), "Belum ada mapping" ) -> Sumatera Utara | M30: =IFERROR(__xludf.DUMMYFUNCTION("IF(REGEXMATCH(I30,""Cari Kerja""),1,0) "),1.0) -> 1 | N30: =IFERROR(__xludf.DUMMYFUNCTION("IF(REGEXMATCH(I30,""Upskill""),1,0) "),0.0) -> 0 | O30: =IFERROR(__xludf.DUMMYFUNCTION("IF(REGEXMATCH(I30,""Networking""),1,0) "),0.0) -> 0 | P30: =IFERROR(__xludf.DUMMYFUNCTION("IF(REGEXMATCH(I30,""Switch Career""),1,0) "),0.0) -> 0
A31: 46047.029 | B31: Ageng Pradikta Maulana | C31: ageng.pradikta@gmail.com | D31: 081228618111 | E31: Malang | F31: Tidak | G31: Sales Area (Infinix Indonesia) | H31: Excel | I31: Cari Kerja, Upskill, Networking, Switch Career | J31: LinkedIn | K31: =IF(LEFT(D31,2)="62","0"&MID(D31,3,LEN(D31)),D31) -> 081228618111 | L31: =IFERROR( VLOOKUP( TRIM( IF(ISNUMBER(FIND(",",E31)), LEFT(E31,FIND(",",E31)-1), E31 ) ), master!A:B, 2, FALSE ), "Belum ada mapping" ) -> Jawa Timur | M31: =IFERROR(__xludf.DUMMYFUNCTION("IF(REGEXMATCH(I31,""Cari Kerja""),1,0) "),1.0) -> 1 | N31: =IFERROR(__xludf.DUMMYFUNCTION("IF(REGEXMATCH(I31,""Upskill""),1,0) "),1.0) -> 1 | O31: =IFERROR(__xludf.DUMMYFUNCTION("IF(REGEXMATCH(I31,""Networking""),1,0) "),1.0) -> 1 | P31: =IFERROR(__xludf.DUMMYFUNCTION("IF(REGEXMATCH(I31,""Switch Career""),1,0) "),1.0) -> 1
A32: 46042.244 | B32: agriffa nuzra djolanda | C32: agriffaanzr@gmail.com | D32: 0895415890030 | E32: Bekasi | F32: Ya | G32: Politeknik Takumi | H32: Excel, Power BI, Looker Studio, Tableau | I32: Cari Kerja, Upskill, Networking, Switch Career | J32: LinkedIn | K32: =IF(LEFT(D32,2)="62","0"&MID(D32,3,LEN(D32)),D32) -> 0895415890030 | L32: =IFERROR( VLOOKUP( TRIM( IF(ISNUMBER(FIND(",",E32)), LEFT(E32,FIND(",",E32)-1), E32 ) ), master!A:B, 2, FALSE ), "Belum ada mapping" ) -> Jawa Barat | M32: =IFERROR(__xludf.DUMMYFUNCTION("IF(REGEXMATCH(I32,""Cari Kerja""),1,0) "),1.0) -> 1 | N32: =IFERROR(__xludf.DUMMYFUNCTION("IF(REGEXMATCH(I32,""Upskill""),1,0) "),1.0) -> 1 | O32: =IFERROR(__xludf.DUMMYFUNCTION("IF(REGEXMATCH(I32,""Networking""),1,0) "),1.0) -> 1 | P32: =IFERROR(__xludf.DUMMYFUNCTION("IF(REGEXMATCH(I32,""Switch Career""),1,0) "),1.0) -> 1
A33: 46046.389 | B33: Agung Nugroho | C33: agg93nugroho@gmail.com | D33: 085117531509 | E33: Jakarta | F33: Tidak | G33: Phl di RS Bhayangkara Tk I Pusdokkes Polri | H33: Excel, SQL, Python, Databases | I33: Cari Kerja, Upskill, Networking, Switch Career | J33: Teman | K33: =IF(LEFT(D33,2)="62","0"&MID(D33,3,LEN(D33)),D33) -> 085117531509 | L33: =IFERROR( VLOOKUP( TRIM( IF(ISNUMBER(FIND(",",E33)), LEFT(E33,FIND(",",E33)-1), E33 ) ), master!A:B, 2, FALSE ), "Belum ada mapping" ) -> Jakarta | M33: =IFERROR(__xludf.DUMMYFUNCTION("IF(REGEXMATCH(I33,""Cari Kerja""),1,0) "),1.0) -> 1 | N33: =IFERROR(__xludf.DUMMYFUNCTION("IF(REGEXMATCH(I33,""Upskill""),1,0) "),1.0) -> 1 | O33: =IFERROR(__xludf.DUMMYFUNCTION("IF(REGEXMATCH(I33,""Networking""),1,0) "),1.0) -> 1 | P33: =IFERROR(__xludf.DUMMYFUNCTION("IF(REGEXMATCH(I33,""Switch Career""),1,0) "),1.0) -> 1
A34: 46042.301 | B34: Agung saputra | C34: agung12saputra2@gmail.com | D34: 081290952870 | E34: Sumatera selatan | F34: Tidak | G34: PT Satria Mayangkara Service | H34: Excel, Looker Studio, Databases | I34: Upskill | J34: LinkedIn | K34: =IF(LEFT(D34,2)="62","0"&MID(D34,3,LEN(D34)),D34) -> 081290952870 | L34: =IFERROR( VLOOKUP( TRIM( IF(ISNUMBER(FIND(",",E34)), LEFT(E34,FIND(",",E34)-1), E34 ) ), master!A:B, 2, FALSE ), "Belum ada mapping" ) -> Sumatera Selatan | M34: =IFERROR(__xludf.DUMMYFUNCTION("IF(REGEXMATCH(I34,""Cari Kerja""),1,0) "),0.0) -> 0 | N34: =IFERROR(__xludf.DUMMYFUNCTION("IF(REGEXMATCH(I34,""Upskill""),1,0) "),1.0) -> 1 | O34: =IFERROR(__xludf.DUMMYFUNCTION("IF(REGEXMATCH(I34,""Networking""),1,0) "),0.0) -> 0 | P34: =IFERROR(__xludf.DUMMYFUNCTION("IF(REGEXMATCH(I34,""Switch Career""),1,0) "),0.0) -> 0
A35: 46048.934 | B35: Agung Turpa | C35: agung.turpa@eatsagala.id | D35: 0895610337754 | E35: Bandung | F35: Tidak | G35: Data operations | H35: Excel, SQL, Python, Databases, Tableau | I35: Upskill, Networking | J35: Teman | K35: =IF(LEFT(D35,2)="62","0"&MID(D35,3,LEN(D35)),D35) -> 0895610337754 | L35: =IFERROR( VLOOKUP( TRIM( IF(ISNUMBER(FIND(",",E35)), LEFT(E35,FIND(",",E35)-1), E35 ) ), master!A:B, 2, FALSE ), "Belum ada mapping" ) -> Jawa Barat | M35: =IFERROR(__xludf.DUMMYFUNCTION("IF(REGEXMATCH(I35,""Cari Kerja""),1,0) "),0.0) -> 0 | N35: =IFERROR(__xludf.DUMMYFUNCTION("IF(REGEXMATCH(I35,""Upskill""),1,0) "),1.0) -> 1 | O35: =IFERROR(__xludf.DUMMYFUNCTION("IF(REGEXMATCH(I35,""Networking""),1,0) "),1.0) -> 1 | P35: =IFERROR(__xludf.DUMMYFUNCTION("IF(REGEXMATCH(I35,""Switch Career""),1,0) "),0.0) -> 0
A36: 46042.327 | B36: Ahmad Aan Said Daroini | C36: ahmadaansaiddaroini@gmail.com | D36: 085608185322 | E36: Surabaya | F36: Tidak | G36: Admin support - PT Garis Pertama Solusi | H36: SQL, Python, Power BI, Looker Studio | I36: Cari Kerja, Upskill, Networking | J36: LinkedIn | K36: =IF(LEFT(D36,2)="62","0"&MID(D36,3,LEN(D36)),D36) -> 085608185322 | L36: =IFERROR( VLOOKUP( TRIM( IF(ISNUMBER(FIND(",",E36)), LEFT(E36,FIND(",",E36)-1), E36 ) ), master!A:B, 2, FALSE ), "Belum ada mapping" ) -> Jawa Timur | M36: =IFERROR(__xludf.DUMMYFUNCTION("IF(REGEXMATCH(I36,""Cari Kerja""),1,0) "),1.0) -> 1 | N36: =IFERROR(__xludf.DUMMYFUNCTION("IF(REGEXMATCH(I36,""Upskill""),1,0) "),1.0) -> 1 | O36: =IFERROR(__xludf.DUMMYFUNCTION("IF(REGEXMATCH(I36,""Networking""),1,0) "),1.0) -> 1 | P36: =IFERROR(__xludf.DUMMYFUNCTION("IF(REGEXMATCH(I36,""Switch Career""),1,0) "),0.0) -> 0
A37: 46042.489 | B37: Ahmad Barra | C37: abvicra@gmail.com | D37: 085156639669 | E37: Jakarta | F37: Tidak | G37: Pegawai Swasta - Corporate Banking Relationship Manager | H37: Excel, SQL, Python, Power BI, Databases, Tableau | I37: Cari Kerja, Upskill, Networking, Switch Career | J37: Instagram | K37: =IF(LEFT(D37,2)="62","0"&MID(D37,3,LEN(D37)),D37) -> 085156639669 | L37: =IFERROR( VLOOKUP( TRIM( IF(ISNUMBER(FIND(",",E37)), LEFT(E37,FIND(",",E37)-1), E37 ) ), master!A:B, 2, FALSE ), "Belum ada mapping" ) -> Jakarta | M37: =IFERROR(__xludf.DUMMYFUNCTION("IF(REGEXMATCH(I37,""Cari Kerja""),1,0) "),1.0) -> 1 | N37: =IFERROR(__xludf.DUMMYFUNCTION("IF(REGEXMATCH(I37,""Upskill""),1,0) "),1.0) -> 1 | O37: =IFERROR(__xludf.DUMMYFUNCTION("IF(REGEXMATCH(I37,""Networking""),1,0) "),1.0) -> 1 | P37: =IFERROR(__xludf.DUMMYFUNCTION("IF(REGEXMATCH(I37,""Switch Career""),1,0) "),1.0) -> 1
A38: 46043.292 | B38: AHMAD FADILLAH HARAHAp | C38: afadillah117@gmail.com | D38: 087768885573 | E38: Medan | F38: Ya | G38: Fresh graduate | H38: Excel, Python, Databases | I38: Cari Kerja, Upskill, Networking, Switch Career | J38: Instagram | K38: =IF(LEFT(D38,2)="62","0"&MID(D38,3,LEN(D38)),D38) -> 087768885573 | L38: =IFERROR( VLOOKUP( TRIM( IF(ISNUMBER(FIND(",",E38)), LEFT(E38,FIND(",",E38)-1), E38 ) ), master!A:B, 2, FALSE ), "Belum ada mapping" ) -> Sumatera Utara | M38: =IFERROR(__xludf.DUMMYFUNCTION("IF(REGEXMATCH(I38,""Cari Kerja""),1,0) "),1.0) -> 1 | N38: =IFERROR(__xludf.DUMMYFUNCTION("IF(REGEXMATCH(I38,""Upskill""),1,0) "),1.0) -> 1 | O38: =IFERROR(__xludf.DUMMYFUNCTION("IF(REGEXMATCH(I38,""Networking""),1,0) "),1.0) -> 1 | P38: =IFERROR(__xludf.DUMMYFUNCTION("IF(REGEXMATCH(I38,""Switch Career""),1,0) "),1.0) -> 1
A39: 46043.262 | B39: Ahmad Fauzi | C39: ahmadfauzi040602@gmail.com | D39: 087781094363 | E39: Tangerang Selatan | F39: Ya | G39: UIN Jakarta | H39: Excel, SQL, Python, Power BI, Looker Studio, Databases, Tableau | I39: Cari Kerja, Upskill, Networking | J39: LinkedIn | K39: =IF(LEFT(D39,2)="62","0"&MID(D39,3,LEN(D39)),D39) -> 087781094363 | L39: =IFERROR( VLOOKUP( TRIM( IF(ISNUMBER(FIND(",",E39)), LEFT(E39,FIND(",",E39)-1), E39 ) ), master!A:B, 2, FALSE ), "Belum ada mapping" ) -> Banten | M39: =IFERROR(__xludf.DUMMYFUNCTION("IF(REGEXMATCH(I39,""Cari Kerja""),1,0) "),1.0) -> 1 | N39: =IFERROR(__xludf.DUMMYFUNCTION("IF(REGEXMATCH(I39,""Upskill""),1,0) "),1.0) -> 1 | O39: =IFERROR(__xludf.DUMMYFUNCTION("IF(REGEXMATCH(I39,""Networking""),1,0) "),1.0) -> 1 | P39: =IFERROR(__xludf.DUMMYFUNCTION("IF(REGEXMATCH(I39,""Switch Career""),1,0) "),0.0) -> 0
A40: 46046.535 | B40: ahmad ilham | C40: bastian.ilham@hotmail.com | D40: 08987503222 | E40: tangerang selatan | F40: Tidak | G40: finance | H40: SQL, Python, Power BI, Looker Studio, Databases, Tableau | I40: Upskill | J40: LinkedIn | K40: =IF(LEFT(D40,2)="62","0"&MID(D40,3,LEN(D40)),D40) -> 08987503222 | L40: =IFERROR( VLOOKUP( TRIM( IF(ISNUMBER(FIND(",",E40)), LEFT(E40,FIND(",",E40)-1), E40 ) ), master!A:B, 2, FALSE ), "Belum ada mapping" ) -> Banten | M40: =IFERROR(__xludf.DUMMYFUNCTION("IF(REGEXMATCH(I40,""Cari Kerja""),1,0) "),0.0) -> 0 | N40: =IFERROR(__xludf.DUMMYFUNCTION("IF(REGEXMATCH(I40,""Upskill""),1,0) "),1.0) -> 1 | O40: =IFERROR(__xludf.DUMMYFUNCTION("IF(REGEXMATCH(I40,""Networking""),1,0) "),0.0) -> 0 | P40: =IFERROR(__xludf.DUMMYFUNCTION("IF(REGEXMATCH(I40,""Switch Career""),1,0) "),0.0) -> 0
A41: 46040.359 | B41: Ahmad MusliADI | C41: ahmadmusliadi.wlp@gmail.com | D41: 085299246868 | E41: Makassar | F41: Tidak | G41: Jobseeker | H41: Excel, SQL, Python, Power BI, Looker Studio, Databases, Tableau | I41: Cari Kerja, Upskill, Networking, Switch Career | J41: LinkedIn | K41: =IF(LEFT(D41,2)="62","0"&MID(D41,3,LEN(D41)),D41) -> 085299246868 | L41: =IFERROR( VLOOKUP( TRIM( IF(ISNUMBER(FIND(",",E41)), LEFT(E41,FIND(",",E41)-1), E41 ) ), master!A:B, 2, FALSE ), "Belum ada mapping" ) -> Sulawesi Selatan | M41: =IFERROR(__xludf.DUMMYFUNCTION("IF(REGEXMATCH(I41,""Cari Kerja""),1,0) "),1.0) -> 1 | N41: =IFERROR(__xludf.DUMMYFUNCTION("IF(REGEXMATCH(I41,""Upskill""),1,0) "),1.0) -> 1 | O41: =IFERROR(__xludf.DUMMYFUNCTION("IF(REGEXMATCH(I41,""Networking""),1,0) "),1.0) -> 1 | P41: =IFERROR(__xludf.DUMMYFUNCTION("IF(REGEXMATCH(I41,""Switch Career""),1,0) "),1.0) -> 1
A42: 46043.267 | B42: Ahmad naziullah | C42: Naziullah7@gmail.com | D42: 08231225280p | E42: Serang | F42: Tidak | G42: - | H42: Excel, SQL, Power BI, | I42: Cari Kerja, Upskill, Switch Career | J42: LinkedIn | K42: =IF(LEFT(D42,2)="62","0"&MID(D42,3,LEN(D42)),D42) -> 08231225280p | L42: =IFERROR( VLOOKUP( TRIM( IF(ISNUMBER(FIND(",",E42)), LEFT(E42,FIND(",",E42)-1), E42 ) ), master!A:B, 2, FALSE ), "Belum ada mapping" ) -> Banten | M42: =IFERROR(__xludf.DUMMYFUNCTION("IF(REGEXMATCH(I42,""Cari Kerja""),1,0) "),1.0) -> 1 | N42: =IFERROR(__xludf.DUMMYFUNCTION("IF(REGEXMATCH(I42,""Upskill""),1,0) "),1.0) -> 1 | O42: =IFERROR(__xludf.DUMMYFUNCTION("IF(REGEXMATCH(I42,""Networking""),1,0) "),0.0) -> 0 | P42: =IFERROR(__xludf.DUMMYFUNCTION("IF(REGEXMATCH(I42,""Switch Career""),1,0) "),1.0) -> 1
A43: 46120.85 | B43: Ahmad Nur Abdullah | C43: ahmadnr360@gmail.com | D43: 081211737531 | E43: Tangerang Selatan | F43: Ya | G43: mahasiswa | H43: Excel, SQL, Python, Power BI, Looker Studio, Databases, Tableau | I43: Cari Kerja, Upskill, Networking | J43: LinkedIn | K43: =IF(LEFT(D43,2)="62","0"&MID(D43,3,LEN(D43)),D43) -> 081211737531 | L43: =IFERROR( VLOOKUP( TRIM( IF(ISNUMBER(FIND(",",E43)), LEFT(E43,FIND(",",E43)-1), E43 ) ), master!A:B, 2, FALSE ), "Belum ada mapping" ) -> Banten | M43: =IFERROR(__xludf.DUMMYFUNCTION("IF(REGEXMATCH(I43,""Cari Kerja""),1,0) "),1.0) -> 1 | N43: =IFERROR(__xludf.DUMMYFUNCTION("IF(REGEXMATCH(I43,""Upskill""),1,0) "),1.0) -> 1 | O43: =IFERROR(__xludf.DUMMYFUNCTION("IF(REGEXMATCH(I43,""Networking""),1,0) "),1.0) -> 1 | P43: =IFERROR(__xludf.DUMMYFUNCTION("IF(REGEXMATCH(I43,""Switch Career""),1,0) "),0.0) -> 0
A44: 46040.413 | B44: Ahmad Raul Sanca Avilio Pratama | C44: ahmadraulsancaaviliopratama@gmail.com | D44: 089614108788 | E44: Malang | F44: Tidak | G44: Business Intelligence | H44: SQL, Python, Power BI, Databases, Tableau | I44: Upskill, Networking, Switch Career | J44: LinkedIn | K44: =IF(LEFT(D44,2)="62","0"&MID(D44,3,LEN(D44)),D44) -> 089614108788 | L44: =IFERROR( VLOOKUP( TRIM( IF(ISNUMBER(FIND(",",E44)), LEFT(E44,FIND(",",E44)-1), E44 ) ), master!A:B, 2, FALSE ), "Belum ada mapping" ) -> Jawa Timur | M44: =IFERROR(__xludf.DUMMYFUNCTION("IF(REGEXMATCH(I44,""Cari Kerja""),1,0) "),0.0) -> 0 | N44: =IFERROR(__xludf.DUMMYFUNCTION("IF(REGEXMATCH(I44,""Upskill""),1,0) "),1.0) -> 1 | O44: =IFERROR(__xludf.DUMMYFUNCTION("IF(REGEXMATCH(I44,""Networking""),1,0) "),1.0) -> 1 | P44: =IFERROR(__xludf.DUMMYFUNCTION("IF(REGEXMATCH(I44,""Switch Career""),1,0) "),1.0) -> 1
A45: 46040.471 | B45: Ahmad Rifat Nur Mustopa | C45: rifatahmad031001@gmail.com | D45: 082279790640 | E45: Jambi | F45: Tidak | G45: Data Management PT Wirakarya Sakti | H45: Excel, SQL, Python, Power BI, Looker Studio, Databases, Tableau | I45: Upskill, Networking, Switch Career | J45: LinkedIn | K45: =IF(LEFT(D45,2)="62","0"&MID(D45,3,LEN(D45)),D45) -> 082279790640 | L45: =IFERROR( VLOOKUP( TRIM( IF(ISNUMBER(FIND(",",E45)), LEFT(E45,FIND(",",E45)-1), E45 ) ), master!A:B, 2, FALSE ), "Belum ada mapping" ) -> Jambi | M45: =IFERROR(__xludf.DUMMYFUNCTION("IF(REGEXMATCH(I45,""Cari Kerja""),1,0) "),0.0) -> 0 | N45: =IFERROR(__xludf.DUMMYFUNCTION("IF(REGEXMATCH(I45,""Upskill""),1,0) "),1.0) -> 1 | O45: =IFERROR(__xludf.DUMMYFUNCTION("IF(REGEXMATCH(I45,""Networking""),1,0) "),1.0) -> 1 | P45: =IFERROR(__xludf.DUMMYFUNCTION("IF(REGEXMATCH(I45,""Switch Career""),1,0) "),1.0) -> 1
A46: 46046.639 | B46: Ahmad Rizki Hardiansyah | C46: ahmadrizkihardiansyah@gmail.com | D46: 088801101132 | E46: Bekasi | F46: Ya | G46: Ojek Online | H46: Excel, SQL, Python, Power BI, Looker Studio, Databases, Tableau | I46: Cari Kerja, Upskill, Networking | J46: LinkedIn | K46: =IF(LEFT(D46,2)="62","0"&MID(D46,3,LEN(D46)),D46) -> 088801101132 | L46: =IFERROR( VLOOKUP( TRIM( IF(ISNUMBER(FIND(",",E46)), LEFT(E46,FIND(",",E46)-1), E46 ) ), master!A:B, 2, FALSE ), "Belum ada mapping" ) -> Jawa Barat | M46: =IFERROR(__xludf.DUMMYFUNCTION("IF(REGEXMATCH(I46,""Cari Kerja""),1,0) "),1.0) -> 1 | N46: =IFERROR(__xludf.DUMMYFUNCTION("IF(REGEXMATCH(I46,""Upskill""),1,0) "),1.0) -> 1 | O46: =IFERROR(__xludf.DUMMYFUNCTION("IF(REGEXMATCH(I46,""Networking""),1,0) "),1.0) -> 1 | P46: =IFERROR(__xludf.DUMMYFUNCTION("IF(REGEXMATCH(I46,""Switch Career""),1,0) "),0.0) -> 0
A47: 46049.295 | B47: Ahmez faisal abdurrahman | C47: Ahmezfaisal21@gmail.com | D47: 087753343987 | E47: Gresik | F47: Tidak | G47: Cpns kemenag | H47: SQL, Python, Power BI, Looker Studio, Databases, Tableau, Data analyst spesifik dunia sosial | I47: Upskill, Networking, Switch Career | J47: Teman | K47: =IF(LEFT(D47,2)="62","0"&MID(D47,3,LEN(D47)),D47) -> 087753343987 | L47: =IFERROR( VLOOKUP( TRIM( IF(ISNUMBER(FIND(",",E47)), LEFT(E47,FIND(",",E47)-1), E47 ) ), master!A:B, 2, FALSE ), "Belum ada mapping" ) -> Jawa Timur | M47: =IFERROR(__xludf.DUMMYFUNCTION("IF(REGEXMATCH(I47,""Cari Kerja""),1,0) "),0.0) -> 0 | N47: =IFERROR(__xludf.DUMMYFUNCTION("IF(REGEXMATCH(I47,""Upskill""),1,0) "),1.0) -> 1 | O47: =IFERROR(__xludf.DUMMYFUNCTION("IF(REGEXMATCH(I47,""Networking""),1,0) "),1.0) -> 1 | P47: =IFERROR(__xludf.DUMMYFUNCTION("IF(REGEXMATCH(I47,""Switch Career""),1,0) "),1.0) -> 1
A48: 46048.809 | B48: Ai Shanti Sugianty | C48: shantisugianty24@gmail.com | D48: 0895333146474 | E48: Jakarta | F48: Ya | G48: - | H48: Excel, SQL, Python, Power BI, Looker Studio, Databases, Tableau | I48: Cari Kerja, Upskill, Networking, Switch Career | J48: LinkedIn | K48: =IF(LEFT(D48,2)="62","0"&MID(D48,3,LEN(D48)),D48) -> 0895333146474 | L48: =IFERROR( VLOOKUP( TRIM( IF(ISNUMBER(FIND(",",E48)), LEFT(E48,FIND(",",E48)-1), E48 ) ), master!A:B, 2, FALSE ), "Belum ada mapping" ) -> Jakarta | M48: =IFERROR(__xludf.DUMMYFUNCTION("IF(REGEXMATCH(I48,""Cari Kerja""),1,0) "),1.0) -> 1 | N48: =IFERROR(__xludf.DUMMYFUNCTION("IF(REGEXMATCH(I48,""Upskill""),1,0) "),1.0) -> 1 | O48: =IFERROR(__xludf.DUMMYFUNCTION("IF(REGEXMATCH(I48,""Networking""),1,0) "),1.0) -> 1 | P48: =IFERROR(__xludf.DUMMYFUNCTION("IF(REGEXMATCH(I48,""Switch Career""),1,0) "),1.0) -> 1
A49: 46056.881 | B49: Aikylla Zahra Permana | C49: aikyllazahra2646@gmail.com | D49: 089669278023 | E49: Purwokerto | F49: Ya | G49: Mahasiswa | H49: Looker Studio, Tableau | I49: Cari Kerja, Upskill, Networking | J49: LinkedIn | K49: =IF(LEFT(D49,2)="62","0"&MID(D49,3,LEN(D49)),D49) -> 089669278023 | L49: =IFERROR( VLOOKUP( TRIM( IF(ISNUMBER(FIND(",",E49)), LEFT(E49,FIND(",",E49)-1), E49 ) ), master!A:B, 2, FALSE ), "Belum ada mapping" ) -> Jawa Tengah | M49: =IFERROR(__xludf.DUMMYFUNCTION("IF(REGEXMATCH(I49,""Cari Kerja""),1,0) "),1.0) -> 1 | N49: =IFERROR(__xludf.DUMMYFUNCTION("IF(REGEXMATCH(I49,""Upskill""),1,0) "),1.0) -> 1 | O49: =IFERROR(__xludf.DUMMYFUNCTION("IF(REGEXMATCH(I49,""Networking""),1,0) "),1.0) -> 1 | P49: =IFERROR(__xludf.DUMMYFUNCTION("IF(REGEXMATCH(I49,""Switch Career""),1,0) "),0.0) -> 0
A50: 46120.618 | B50: Ainayah Alfatihah | C50: ainayahalfatihah26@gmail.com | D50: 089696851417 | E50: Malang | F50: Ya | G50: Mahasiswa dan Freelance | H50: SQL, Python, Power BI, Looker Studio | I50: Networking | J50: LinkedIn | K50: =IF(LEFT(D50,2)="62","0"&MID(D50,3,LEN(D50)),D50) -> 089696851417 | L50: =IFERROR( VLOOKUP( TRIM( IF(ISNUMBER(FIND(",",E50)), LEFT(E50,FIND(",",E50)-1), E50 ) ), master!A:B, 2, FALSE ), "Belum ada mapping" ) -> Jawa Timur | M50: =IFERROR(__xludf.DUMMYFUNCTION("IF(REGEXMATCH(I50,""Cari Kerja""),1,0) "),0.0) -> 0 | N50: =IFERROR(__xludf.DUMMYFUNCTION("IF(REGEXMATCH(I50,""Upskill""),1,0) "),0.0) -> 0 | O50: =IFERROR(__xludf.DUMMYFUNCTION("IF(REGEXMATCH(I50,""Networking""),1,0) "),1.0) -> 1 | P50: =IFERROR(__xludf.DUMMYFUNCTION("IF(REGEXMATCH(I50,""Switch Career""),1,0) "),0.0) -> 0
A51: 46122.613 | B51: Aisyah Kirana Putri Isyanto | C51: aisyahisyanto@gmail.com | D51: 081234909715 | E51: Mojokerto | F51: Ya | G51: Data Analyst Support - Statsme | H51: SQL, Python, Databases | I51: Upskill, Networking | J51: Teman | K51: =IF(LEFT(D51,2)="62","0"&MID(D51,3,LEN(D51)),D51) -> 081234909715 | L51: =IFERROR( VLOOKUP( TRIM( IF(ISNUMBER(FIND(",",E51)), LEFT(E51,FIND(",",E51)-1), E51 ) ), master!A:B, 2, FALSE ), "Belum ada mapping" ) -> Jawa Timur | M51: =IFERROR(__xludf.DUMMYFUNCTION("IF(REGEXMATCH(I51,""Cari Kerja""),1,0) "),0.0) -> 0 | N51: =IFERROR(__xludf.DUMMYFUNCTION("IF(REGEXMATCH(I51,""Upskill""),1,0) "),1.0) -> 1 | O51: =IFERROR(__xludf.DUMMYFUNCTION("IF(REGEXMATCH(I51,""Networking""),1,0) "),1.0) -> 1 | P51: =IFERROR(__xludf.DUMMYFUNCTION("IF(REGEXMATCH(I51,""Switch Career""),1,0) "),0.0) -> 0
A52: 46049.522 | B52: Aisyah Nuraini | C52: nurainiaisyah724@gmail.com | D52: 0858-9028-4815 | E52: Tangerang | F52: Ya | G52: Fresh Graduate | H52: Excel, SQL, Python, Power BI, Looker Studio, Databases, Tableau | I52: Cari Kerja, Upskill | J52: LinkedIn | K52: =IF(LEFT(D52,2)="62","0"&MID(D52,3,LEN(D52)),D52) -> 0858-9028-4815 | L52: =IFERROR( VLOOKUP( TRIM( IF(ISNUMBER(FIND(",",E52)), LEFT(E52,FIND(",",E52)-1), E52 ) ), master!A:B, 2, FALSE ), "Belum ada mapping" ) -> Banten | M52: =IFERROR(__xludf.DUMMYFUNCTION("IF(REGEXMATCH(I52,""Cari Kerja""),1,0) "),1.0) -> 1 | N52: =IFERROR(__xludf.DUMMYFUNCTION("IF(REGEXMATCH(I52,""Upskill""),1,0) "),1.0) -> 1 | O52: =IFERROR(__xludf.DUMMYFUNCTION("IF(REGEXMATCH(I52,""Networking""),1,0) "),0.0) -> 0 | P52: =IFERROR(__xludf.DUMMYFUNCTION("IF(REGEXMATCH(I52,""Switch Career""),1,0) "),0.0) -> 0
A53: 46040.346 | B53: Aisyah Syafa Azzahra | C53: aisyahsyafazzahra@gmail.com | D53: 085934847451 | E53: Tangerang | F53: Ya | G53: PT Zyrexindo Mandiri Buana Tbk | H53: Excel, SQL, Python, Power BI, Looker Studio, Databases, Tableau, Semua Tools Data Analyst | I53: Cari Kerja, Upskill, Networking | J53: LinkedIn | K53: =IF(LEFT(D53,2)="62","0"&MID(D53,3,LEN(D53)),D53) -> 085934847451 | L53: =IFERROR( VLOOKUP( TRIM( IF(ISNUMBER(FIND(",",E53)), LEFT(E53,FIND(",",E53)-1), E53 ) ), master!A:B, 2, FALSE ), "Belum ada mapping" ) -> Banten | M53: =IFERROR(__xludf.DUMMYFUNCTION("IF(REGEXMATCH(I53,""Cari Kerja""),1,0) "),1.0) -> 1 | N53: =IFERROR(__xludf.DUMMYFUNCTION("IF(REGEXMATCH(I53,""Upskill""),1,0) "),1.0) -> 1 | O53: =IFERROR(__xludf.DUMMYFUNCTION("IF(REGEXMATCH(I53,""Networking""),1,0) "),1.0) -> 1 | P53: =IFERROR(__xludf.DUMMYFUNCTION("IF(REGEXMATCH(I53,""Switch Career""),1,0) "),0.0) -> 0
A54: 46042.448 | B54: Akbar Fadhillah Irsyad Usman | C54: akbarfiusman@gmail.com | D54: 083188233315 | E54: Tangerang | F54: Tidak | G54: karyawan swasta | H54: Excel, SQL, Python, Power BI, Looker Studio, Databases, Tableau | I54: Cari Kerja, Upskill, Networking | J54: LinkedIn | K54: =IF(LEFT(D54,2)="62","0"&MID(D54,3,LEN(D54)),D54) -> 083188233315 | L54: =IFERROR( VLOOKUP( TRIM( IF(ISNUMBER(FIND(",",E54)), LEFT(E54,FIND(",",E54)-1), E54 ) ), master!A:B, 2, FALSE ), "Belum ada mapping" ) -> Banten | M54: =IFERROR(__xludf.DUMMYFUNCTION("IF(REGEXMATCH(I54,""Cari Kerja""),1,0) "),1.0) -> 1 | N54: =IFERROR(__xludf.DUMMYFUNCTION("IF(REGEXMATCH(I54,""Upskill""),1,0) "),1.0) -> 1 | O54: =IFERROR(__xludf.DUMMYFUNCTION("IF(REGEXMATCH(I54,""Networking""),1,0) "),1.0) -> 1 | P54: =IFERROR(__xludf.DUMMYFUNCTION("IF(REGEXMATCH(I54,""Switch Career""),1,0) "),0.0) -> 0
A55: 46042.56 | B55: Aksa | C55: wicaaksaana@gmail.com | D55: 0813432159315 | E55: Jakarta | F55: Ya | G55: - | H55: Looker Studio, Databases, Tableau | I55: Upskill, Networking, Switch Career | J55: LinkedIn | K55: =IF(LEFT(D55,2)="62","0"&MID(D55,3,LEN(D55)),D55) -> 0813432159315 | L55: =IFERROR( VLOOKUP( TRIM( IF(ISNUMBER(FIND(",",E55)), LEFT(E55,FIND(",",E55)-1), E55 ) ), master!A:B, 2, FALSE ), "Belum ada mapping" ) -> Jakarta | M55: =IFERROR(__xludf.DUMMYFUNCTION("IF(REGEXMATCH(I55,""Cari Kerja""),1,0) "),0.0) -> 0 | N55: =IFERROR(__xludf.DUMMYFUNCTION("IF(REGEXMATCH(I55,""Upskill""),1,0) "),1.0) -> 1 | O55: =IFERROR(__xludf.DUMMYFUNCTION("IF(REGEXMATCH(I55,""Networking""),1,0) "),1.0) -> 1 | P55: =IFERROR(__xludf.DUMMYFUNCTION("IF(REGEXMATCH(I55,""Switch Career""),1,0) "),1.0) -> 1
A56: 46040.427 | B56: Al Furkan | C56: alfurkannul098@gmail.com | D56: 085238912981 | E56: Palangkaraya Kalimantan Tengah | F56: Tidak | G56: PT. Gojek Tokopedia | H56: SQL | I56: Upskill, Networking, Switch Career | J56: LinkedIn | K56: =IF(LEFT(D56,2)="62","0"&MID(D56,3,LEN(D56)),D56) -> 085238912981 | L56: =IFERROR( VLOOKUP( TRIM( IF(ISNUMBER(FIND(",",E56)), LEFT(E56,FIND(",",E56)-1), E56 ) ), master!A:B, 2, FALSE ), "Belum ada mapping" ) -> Kalimatan Tengah | M56: =IFERROR(__xludf.DUMMYFUNCTION("IF(REGEXMATCH(I56,""Cari Kerja""),1,0) "),0.0) -> 0 | N56: =IFERROR(__xludf.DUMMYFUNCTION("IF(REGEXMATCH(I56,""Upskill""),1,0) "),1.0) -> 1 | O56: =IFERROR(__xludf.DUMMYFUNCTION("IF(REGEXMATCH(I56,""Networking""),1,0) "),1.0) -> 1 | P56: =IFERROR(__xludf.DUMMYFUNCTION("IF(REGEXMATCH(I56,""Switch Career""),1,0) "),1.0) -> 1
A57: 46046.408 | B57: Alana Nur Fathu | C57: alananf97@gmail.com | D57: 085540628464 | E57: Jawa Tengah | F57: Ya | G57: Mahasiswa | H57: Excel, SQL, Python, Tableau | I57: Cari Kerja | J57: Teman | K57: =IF(LEFT(D57,2)="62","0"&MID(D57,3,LEN(D57)),D57) -> 085540628464 | L57: =IFERROR( VLOOKUP( TRIM( IF(ISNUMBER(FIND(",",E57)), LEFT(E57,FIND(",",E57)-1), E57 ) ), master!A:B, 2, FALSE ), "Belum ada mapping" ) -> Jawa Tengah | M57: =IFERROR(__xludf.DUMMYFUNCTION("IF(REGEXMATCH(I57,""Cari Kerja""),1,0) "),1.0) -> 1 | N57: =IFERROR(__xludf.DUMMYFUNCTION("IF(REGEXMATCH(I57,""Upskill""),1,0) "),0.0) -> 0 | O57: =IFERROR(__xludf.DUMMYFUNCTION("IF(REGEXMATCH(I57,""Networking""),1,0) "),0.0) -> 0 | P57: =IFERROR(__xludf.DUMMYFUNCTION("IF(REGEXMATCH(I57,""Switch Career""),1,0) "),0.0) -> 0
A58: 46042.416 | B58: Alexander Sinar W | C58: Sinar1005@gmail.com | D58: 089570916382 | E58: Jember | F58: Ya | G58: Mahasiswa semester 2 | H58: Excel, SQL, Python, Databases, Tableau | I58: Cari Kerja, Upskill, Networking | J58: LinkedIn | K58: =IF(LEFT(D58,2)="62","0"&MID(D58,3,LEN(D58)),D58) -> 089570916382 | L58: =IFERROR( VLOOKUP( TRIM( IF(ISNUMBER(FIND(",",E58)), LEFT(E58,FIND(",",E58)-1), E58 ) ), master!A:B, 2, FALSE ), "Belum ada mapping" ) -> Jawa Timur | M58: =IFERROR(__xludf.DUMMYFUNCTION("IF(REGEXMATCH(I58,""Cari Kerja""),1,0) "),1.0) -> 1 | N58: =IFERROR(__xludf.DUMMYFUNCTION("IF(REGEXMATCH(I58,""Upskill""),1,0) "),1.0) -> 1 | O58: =IFERROR(__xludf.DUMMYFUNCTION("IF(REGEXMATCH(I58,""Networking""),1,0) "),1.0) -> 1 | P58: =IFERROR(__xludf.DUMMYFUNCTION("IF(REGEXMATCH(I58,""Switch Career""),1,0) "),0.0) -> 0
A59: 46044.505 | B59: Alfini Yuliyanti | C59: fin.alfini127@gmail.com | D59: 085156514460 | E59: Jakarta | F59: Tidak | G59: Business Data Analis | H59: Python, Power BI, Looker Studio, Databases, Tableau | I59: Upskill | J59: LinkedIn | K59: =IF(LEFT(D59,2)="62","0"&MID(D59,3,LEN(D59)),D59) -> 085156514460 | L59: =IFERROR( VLOOKUP( TRIM( IF(ISNUMBER(FIND(",",E59)), LEFT(E59,FIND(",",E59)-1), E59 ) ), master!A:B, 2, FALSE ), "Belum ada mapping" ) -> Jakarta | M59: =IFERROR(__xludf.DUMMYFUNCTION("IF(REGEXMATCH(I59,""Cari Kerja""),1,0) "),0.0) -> 0 | N59: =IFERROR(__xludf.DUMMYFUNCTION("IF(REGEXMATCH(I59,""Upskill""),1,0) "),1.0) -> 1 | O59: =IFERROR(__xludf.DUMMYFUNCTION("IF(REGEXMATCH(I59,""Networking""),1,0) "),0.0) -> 0 | P59: =IFERROR(__xludf.DUMMYFUNCTION("IF(REGEXMATCH(I59,""Switch Career""),1,0) "),0.0) -> 0
A60: 46055.865 | B60: Ali Rohman | C60: alirohman56@gmail.com | D60: 089669232481 | E60: Bekasi | F60: Tidak | G60: Coordinator Application Development - PT Multi Kontrol Nusantara | H60: ETL | I60: Cari Kerja, Upskill, Networking | J60: LinkedIn | K60: =IF(LEFT(D60,2)="62","0"&MID(D60,3,LEN(D60)),D60) -> 089669232481 | L60: =IFERROR( VLOOKUP( TRIM( IF(ISNUMBER(FIND(",",E60)), LEFT(E60,FIND(",",E60)-1), E60 ) ), master!A:B, 2, FALSE ), "Belum ada mapping" ) -> Jawa Barat | M60: =IFERROR(__xludf.DUMMYFUNCTION("IF(REGEXMATCH(I60,""Cari Kerja""),1,0) "),1.0) -> 1 | N60: =IFERROR(__xludf.DUMMYFUNCTION("IF(REGEXMATCH(I60,""Upskill""),1,0) "),1.0) -> 1 | O60: =IFERROR(__xludf.DUMMYFUNCTION("IF(REGEXMATCH(I60,""Networking""),1,0) "),1.0) -> 1 | P60: =IFERROR(__xludf.DUMMYFUNCTION("IF(REGEXMATCH(I60,""Switch Career""),1,0) "),0.0) -> 0
A61: 46042.556 | B61: Alief Akbar | C61: alivenata@gmail.com | D61: 08119365633 | E61: Jakarta | F61: Tidak | G61: Data Enginner & Telkomsel | H61: Hadoop, Hive Server | I61: Upskill, Networking | J61: LinkedIn | K61: =IF(LEFT(D61,2)="62","0"&MID(D61,3,LEN(D61)),D61) -> 08119365633 | L61: =IFERROR( VLOOKUP( TRIM( IF(ISNUMBER(FIND(",",E61)), LEFT(E61,FIND(",",E61)-1), E61 ) ), master!A:B, 2, FALSE ), "Belum ada mapping" ) -> Jakarta | M61: =IFERROR(__xludf.DUMMYFUNCTION("IF(REGEXMATCH(I61,""Cari Kerja""),1,0) "),0.0) -> 0 | N61: =IFERROR(__xludf.DUMMYFUNCTION("IF(REGEXMATCH(I61,""Upskill""),1,0) "),1.0) -> 1 | O61: =IFERROR(__xludf.DUMMYFUNCTION("IF(REGEXMATCH(I61,""Networking""),1,0) "),1.0) -> 1 | P61: =IFERROR(__xludf.DUMMYFUNCTION("IF(REGEXMATCH(I61,""Switch Career""),1,0) "),0.0) -> 0
A62: 46046.372 | B62: Alief Akbar | C62: alivenata@gmail.com | D62: 081219365633 | E62: Jakarta Utara | F62: Tidak | G62: Data Engineer & Automation reporting | H62: Tableau | I62: Networking | J62: LinkedIn | K62: =IF(LEFT(D62,2)="62","0"&MID(D62,3,LEN(D62)),D62) -> 081219365633 | L62: =IFERROR( VLOOKUP( TRIM( IF(ISNUMBER(FIND(",",E62)), LEFT(E62,FIND(",",E62)-1), E62 ) ), master!A:B, 2, FALSE ), "Belum ada mapping" ) -> Jakarta | M62: =IFERROR(__xludf.DUMMYFUNCTION("IF(REGEXMATCH(I62,""Cari Kerja""),1,0) "),0.0) -> 0 | N62: =IFERROR(__xludf.DUMMYFUNCTION("IF(REGEXMATCH(I62,""Upskill""),1,0) "),0.0) -> 0 | O62: =IFERROR(__xludf.DUMMYFUNCTION("IF(REGEXMATCH(I62,""Networking""),1,0) "),1.0) -> 1 | P62: =IFERROR(__xludf.DUMMYFUNCTION("IF(REGEXMATCH(I62,""Switch Career""),1,0) "),0.0) -> 0
A63: 46040.485 | B63: alisa salsabila | C63: alisasalsabila0673@gmail.com | D63: 082331360179 | E63: surabaya | F63: Tidak | G63: data analyst pt ratna asia | H63: SQL, Databases, Tableau | I63: Upskill | J63: LinkedIn | K63: =IF(LEFT(D63,2)="62","0"&MID(D63,3,LEN(D63)),D63) -> 082331360179 | L63: =IFERROR( VLOOKUP( TRIM( IF(ISNUMBER(FIND(",",E63)), LEFT(E63,FIND(",",E63)-1), E63 ) ), master!A:B, 2, FALSE ), "Belum ada mapping" ) -> Jawa Timur | M63: =IFERROR(__xludf.DUMMYFUNCTION("IF(REGEXMATCH(I63,""Cari Kerja""),1,0) "),0.0) -> 0 | N63: =IFERROR(__xludf.DUMMYFUNCTION("IF(REGEXMATCH(I63,""Upskill""),1,0) "),1.0) -> 1 | O63: =IFERROR(__xludf.DUMMYFUNCTION("IF(REGEXMATCH(I63,""Networking""),1,0) "),0.0) -> 0 | P63: =IFERROR(__xludf.DUMMYFUNCTION("IF(REGEXMATCH(I63,""Switch Career""),1,0) "),0.0) -> 0
A64: 46042.826 | B64: Alisyah Permatasari | C64: permata.alisy@gmail.com | D64: 085179802420 | E64: Jakarta | F64: Tidak | G64: Inventory Management & Cipta Kridatama | H64: Excel, SQL, Power BI, Databases, Tableau | I64: Upskill, Networking | J64: LinkedIn | K64: =IF(LEFT(D64,2)="62","0"&MID(D64,3,LEN(D64)),D64) -> 085179802420 | L64: =IFERROR( VLOOKUP( TRIM( IF(ISNUMBER(FIND(",",E64)), LEFT(E64,FIND(",",E64)-1), E64 ) ), master!A:B, 2, FALSE ), "Belum ada mapping" ) -> Jakarta | M64: =IFERROR(__xludf.DUMMYFUNCTION("IF(REGEXMATCH(I64,""Cari Kerja""),1,0) "),0.0) -> 0 | N64: =IFERROR(__xludf.DUMMYFUNCTION("IF(REGEXMATCH(I64,""Upskill""),1,0) "),1.0) -> 1 | O64: =IFERROR(__xludf.DUMMYFUNCTION("IF(REGEXMATCH(I64,""Networking""),1,0) "),1.0) -> 1 | P64: =IFERROR(__xludf.DUMMYFUNCTION("IF(REGEXMATCH(I64,""Switch Career""),1,0) "),0.0) -> 0
A65: 46042.663 | B65: Alvita Ambarsari | C65: alvitaambarsa@gmail.com | D65: 085325110545 | E65: Surabaya | F65: Ya | G65: Universitas Teknologi Surabaya | H65: Excel, SQL, Python, Looker Studio, Databases | I65: Cari Kerja, Upskill, Networking, Switch Career | J65: Teman | K65: =IF(LEFT(D65,2)="62","0"&MID(D65,3,LEN(D65)),D65) -> 085325110545 | L65: =IFERROR( VLOOKUP( TRIM( IF(ISNUMBER(FIND(",",E65)), LEFT(E65,FIND(",",E65)-1), E65 ) ), master!A:B, 2, FALSE ), "Belum ada mapping" ) -> Jawa Timur | M65: =IFERROR(__xludf.DUMMYFUNCTION("IF(REGEXMATCH(I65,""Cari Kerja""),1,0) "),1.0) -> 1 | N65: =IFERROR(__xludf.DUMMYFUNCTION("IF(REGEXMATCH(I65,""Upskill""),1,0) "),1.0) -> 1 | O65: =IFERROR(__xludf.DUMMYFUNCTION("IF(REGEXMATCH(I65,""Networking""),1,0) "),1.0) -> 1 | P65: =IFERROR(__xludf.DUMMYFUNCTION("IF(REGEXMATCH(I65,""Switch Career""),1,0) "),1.0) -> 1
A66: 46044.321 | B66: Alvito Prasetyo | C66: alvitoaha05@gmail.com | D66: 085156374617 | E66: Tangerang | F66: Ya | G66: Chemical Researchwr | H66: Python, Power BI, Looker Studio, Databases | I66: Cari Kerja, Upskill, Networking, Switch Career | J66: LinkedIn | K66: =IF(LEFT(D66,2)="62","0"&MID(D66,3,LEN(D66)),D66) -> 085156374617 | L66: =IFERROR( VLOOKUP( TRIM( IF(ISNUMBER(FIND(",",E66)), LEFT(E66,FIND(",",E66)-1), E66 ) ), master!A:B, 2, FALSE ), "Belum ada mapping" ) -> Banten | M66: =IFERROR(__xludf.DUMMYFUNCTION("IF(REGEXMATCH(I66,""Cari Kerja""),1,0) "),1.0) -> 1 | N66: =IFERROR(__xludf.DUMMYFUNCTION("IF(REGEXMATCH(I66,""Upskill""),1,0) "),1.0) -> 1 | O66: =IFERROR(__xludf.DUMMYFUNCTION("IF(REGEXMATCH(I66,""Networking""),1,0) "),1.0) -> 1 | P66: =IFERROR(__xludf.DUMMYFUNCTION("IF(REGEXMATCH(I66,""Switch Career""),1,0) "),1.0) -> 1
A67: 46040.36 | B67: Amalia Arinal Haq | C67: amalhaq3112@gmail.com | D67: 083854425802 | E67: Sidoarjo | F67: Ya | G67: PT. Tiga Berlian Mandiri | H67: SQL, Python, Power BI, Looker Studio, Databases, Tableau | I67: Cari Kerja, Upskill, Networking | J67: LinkedIn | K67: =IF(LEFT(D67,2)="62","0"&MID(D67,3,LEN(D67)),D67) -> 083854425802 | L67: =IFERROR( VLOOKUP( TRIM( IF(ISNUMBER(FIND(",",E67)), LEFT(E67,FIND(",",E67)-1), E67 ) ), master!A:B, 2, FALSE ), "Belum ada mapping" ) -> Jawa Timur | M67: =IFERROR(__xludf.DUMMYFUNCTION("IF(REGEXMATCH(I67,""Cari Kerja""),1,0) "),1.0) -> 1 | N67: =IFERROR(__xludf.DUMMYFUNCTION("IF(REGEXMATCH(I67,""Upskill""),1,0) "),1.0) -> 1 | O67: =IFERROR(__xludf.DUMMYFUNCTION("IF(REGEXMATCH(I67,""Networking""),1,0) "),1.0) -> 1 | P67: =IFERROR(__xludf.DUMMYFUNCTION("IF(REGEXMATCH(I67,""Switch Career""),1,0) "),0.0) -> 0
A68: 46051.601 | B68: Amalia Putri | C68: amaliaputriii27@gmail.com | D68: 088985245151 | E68: Surabaya | F68: Ya | G68: Universitas Negeri Surabaya | H68: Excel, SQL, Python, Power BI, Looker Studio, Databases, Tableau | I68: Cari Kerja, Upskill, Networking | J68: LinkedIn | K68: =IF(LEFT(D68,2)="62","0"&MID(D68,3,LEN(D68)),D68) -> 088985245151 | L68: =IFERROR( VLOOKUP( TRIM( IF(ISNUMBER(FIND(",",E68)), LEFT(E68,FIND(",",E68)-1), E68 ) ), master!A:B, 2, FALSE ), "Belum ada mapping" ) -> Jawa Timur | M68: =IFERROR(__xludf.DUMMYFUNCTION("IF(REGEXMATCH(I68,""Cari Kerja""),1,0) "),1.0) -> 1 | N68: =IFERROR(__xludf.DUMMYFUNCTION("IF(REGEXMATCH(I68,""Upskill""),1,0) "),1.0) -> 1 | O68: =IFERROR(__xludf.DUMMYFUNCTION("IF(REGEXMATCH(I68,""Networking""),1,0) "),1.0) -> 1 | P68: =IFERROR(__xludf.DUMMYFUNCTION("IF(REGEXMATCH(I68,""Switch Career""),1,0) "),0.0) -> 0
A69: 46041.693 | B69: AMANG MISBAH | C69: amangmisbah52@gmail.com | D69: 082321118508 | E69: Jakarta Selatan | F69: Tidak | G69: Data Engineer | H69: Excel, SQL, Python, Databases | I69: Upskill, Networking | J69: LinkedIn | K69: =IF(LEFT(D69,2)="62","0"&MID(D69,3,LEN(D69)),D69) -> 082321118508 | L69: =IFERROR( VLOOKUP( TRIM( IF(ISNUMBER(FIND(",",E69)), LEFT(E69,FIND(",",E69)-1), E69 ) ), master!A:B, 2, FALSE ), "Belum ada mapping" ) -> Jakarta | M69: =IFERROR(__xludf.DUMMYFUNCTION("IF(REGEXMATCH(I69,""Cari Kerja""),1,0) "),0.0) -> 0 | N69: =IFERROR(__xludf.DUMMYFUNCTION("IF(REGEXMATCH(I69,""Upskill""),1,0) "),1.0) -> 1 | O69: =IFERROR(__xludf.DUMMYFUNCTION("IF(REGEXMATCH(I69,""Networking""),1,0) "),1.0) -> 1 | P69: =IFERROR(__xludf.DUMMYFUNCTION("IF(REGEXMATCH(I69,""Switch Career""),1,0) "),0.0) -> 0
A70: 46040.359 | B70: Amelia Fadhillah | C70: ameliafadhillah57@gmail.com | D70: 087808009547 | E70: Bandung | F70: Tidak | G70: Data Analyst | H70: SQL, Python, Power BI, Databases | I70: Upskill, Networking | J70: LinkedIn | K70: =IF(LEFT(D70,2)="62","0"&MID(D70,3,LEN(D70)),D70) -> 087808009547 | L70: =IFERROR( VLOOKUP( TRIM( IF(ISNUMBER(FIND(",",E70)), LEFT(E70,FIND(",",E70)-1), E70 ) ), master!A:B, 2, FALSE ), "Belum ada mapping" ) -> Jawa Barat | M70: =IFERROR(__xludf.DUMMYFUNCTION("IF(REGEXMATCH(I70,""Cari Kerja""),1,0) "),0.0) -> 0 | N70: =IFERROR(__xludf.DUMMYFUNCTION("IF(REGEXMATCH(I70,""Upskill""),1,0) "),1.0) -> 1 | O70: =IFERROR(__xludf.DUMMYFUNCTION("IF(REGEXMATCH(I70,""Networking""),1,0) "),1.0) -> 1 | P70: =IFERROR(__xludf.DUMMYFUNCTION("IF(REGEXMATCH(I70,""Switch Career""),1,0) "),0.0) -> 0
A71: 46042.794 | B71: Amru | C71: kanshayami@gmail.com | D71: 082187775702 | E71: Jakarta | F71: Ya | G71: Mahasiswa | H71: Excel, SQL, Python, Looker Studio, Databases | I71: Upskill, Networking | J71: LinkedIn | K71: =IF(LEFT(D71,2)="62","0"&MID(D71,3,LEN(D71)),D71) -> 082187775702 | L71: =IFERROR( VLOOKUP( TRIM( IF(ISNUMBER(FIND(",",E71)), LEFT(E71,FIND(",",E71)-1), E71 ) ), master!A:B, 2, FALSE ), "Belum ada mapping" ) -> Jakarta | M71: =IFERROR(__xludf.DUMMYFUNCTION("IF(REGEXMATCH(I71,""Cari Kerja""),1,0) "),0.0) -> 0 | N71: =IFERROR(__xludf.DUMMYFUNCTION("IF(REGEXMATCH(I71,""Upskill""),1,0) "),1.0) -> 1 | O71: =IFERROR(__xludf.DUMMYFUNCTION("IF(REGEXMATCH(I71,""Networking""),1,0) "),1.0) -> 1 | P71: =IFERROR(__xludf.DUMMYFUNCTION("IF(REGEXMATCH(I71,""Switch Career""),1,0) "),0.0) -> 0
A72: 46041.464 | B72: Ana Eta Hidayati | C72: Hidayatianaeta@gmail.com | D72: 085159030133 | E72: Bekasi | F72: Tidak | G72: Business development & Global Putra Internasional Group | H72: Excel, SQL, Python, Power BI, Databases | I72: Cari Kerja, Upskill, Networking, Switch Career | J72: LinkedIn | K72: =IF(LEFT(D72,2)="62","0"&MID(D72,3,LEN(D72)),D72) -> 085159030133 | L72: =IFERROR( VLOOKUP( TRIM( IF(ISNUMBER(FIND(",",E72)), LEFT(E72,FIND(",",E72)-1), E72 ) ), master!A:B, 2, FALSE ), "Belum ada mapping" ) -> Jawa Barat | M72: =IFERROR(__xludf.DUMMYFUNCTION("IF(REGEXMATCH(I72,""Cari Kerja""),1,0) "),1.0) -> 1 | N72: =IFERROR(__xludf.DUMMYFUNCTION("IF(REGEXMATCH(I72,""Upskill""),1,0) "),1.0) -> 1 | O72: =IFERROR(__xludf.DUMMYFUNCTION("IF(REGEXMATCH(I72,""Networking""),1,0) "),1.0) -> 1 | P72: =IFERROR(__xludf.DUMMYFUNCTION("IF(REGEXMATCH(I72,""Switch Career""),1,0) "),1.0) -> 1
A73: 46047.779 | B73: Ananda Chindi Dwi Putri | C73: anandachindi6@gmail.com | D73: 085821913174 | E73: Palangkaraya | F73: Ya | G73: - | H73: Excel, SQL, Python, Databases | I73: Upskill, Networking | J73: Teman | K73: =IF(LEFT(D73,2)="62","0"&MID(D73,3,LEN(D73)),D73) -> 085821913174 | L73: =IFERROR( VLOOKUP( TRIM( IF(ISNUMBER(FIND(",",E73)), LEFT(E73,FIND(",",E73)-1), E73 ) ), master!A:B, 2, FALSE ), "Belum ada mapping" ) -> Kalimantan Tengah | M73: =IFERROR(__xludf.DUMMYFUNCTION("IF(REGEXMATCH(I73,""Cari Kerja""),1,0) "),0.0) -> 0 | N73: =IFERROR(__xludf.DUMMYFUNCTION("IF(REGEXMATCH(I73,""Upskill""),1,0) "),1.0) -> 1 | O73: =IFERROR(__xludf.DUMMYFUNCTION("IF(REGEXMATCH(I73,""Networking""),1,0) "),1.0) -> 1 | P73: =IFERROR(__xludf.DUMMYFUNCTION("IF(REGEXMATCH(I73,""Switch Career""),1,0) "),0.0) -> 0
A74: 46041.416 | B74: Andarias | C74: alexaaudrey345@gmail.com | D74: 082155892535 | E74: Balikpapan | F74: Tidak | G74: 0 | H74: Python, Power BI, Looker Studio, Databases | I74: Cari Kerja, Upskill, Networking | J74: LinkedIn | K74: =IF(LEFT(D74,2)="62","0"&MID(D74,3,LEN(D74)),D74) -> 082155892535 | L74: =IFERROR( VLOOKUP( TRIM( IF(ISNUMBER(FIND(",",E74)), LEFT(E74,FIND(",",E74)-1), E74 ) ), master!A:B, 2, FALSE ), "Belum ada mapping" ) -> Kalimantan Timur | M74: =IFERROR(__xludf.DUMMYFUNCTION("IF(REGEXMATCH(I74,""Cari Kerja""),1,0) "),1.0) -> 1 | N74: =IFERROR(__xludf.DUMMYFUNCTION("IF(REGEXMATCH(I74,""Upskill""),1,0) "),1.0) -> 1 | O74: =IFERROR(__xludf.DUMMYFUNCTION("IF(REGEXMATCH(I74,""Networking""),1,0) "),1.0) -> 1 | P74: =IFERROR(__xludf.DUMMYFUNCTION("IF(REGEXMATCH(I74,""Switch Career""),1,0) "),0.0) -> 0
A75: 46065.788 | B75: Andhika | C75: andikaquimico@gmail.com | D75: 085363008069 | E75: PARINGIN | F75: Tidak | G75: WIRASWASTA | H75: Excel, SQL, Power BI, Databases | I75: Upskill, Networking | J75: LinkedIn | K75: =IF(LEFT(D75,2)="62","0"&MID(D75,3,LEN(D75)),D75) -> 085363008069 | L75: =IFERROR( VLOOKUP( TRIM( IF(ISNUMBER(FIND(",",E75)), LEFT(E75,FIND(",",E75)-1), E75 ) ), master!A:B, 2, FALSE ), "Belum ada mapping" ) -> Kalimantan Selatan | M75: =IFERROR(__xludf.DUMMYFUNCTION("IF(REGEXMATCH(I75,""Cari Kerja""),1,0) "),0.0) -> 0 | N75: =IFERROR(__xludf.DUMMYFUNCTION("IF(REGEXMATCH(I75,""Upskill""),1,0) "),1.0) -> 1 | O75: =IFERROR(__xludf.DUMMYFUNCTION("IF(REGEXMATCH(I75,""Networking""),1,0) "),1.0) -> 1 | P75: =IFERROR(__xludf.DUMMYFUNCTION("IF(REGEXMATCH(I75,""Switch Career""),1,0) "),0.0) -> 0
A76: 46041.424 | B76: Andi Mamhola | C76: exaudi.ljp@gmail.com | D76: 0895321338951 | E76: Medan | F76: Tidak | G76: Pemerintahan | H76: SQL, Looker Studio | I76: Upskill | J76: LinkedIn | K76: =IF(LEFT(D76,2)="62","0"&MID(D76,3,LEN(D76)),D76) -> 0895321338951 | L76: =IFERROR( VLOOKUP( TRIM( IF(ISNUMBER(FIND(",",E76)), LEFT(E76,FIND(",",E76)-1), E76 ) ), master!A:B, 2, FALSE ), "Belum ada mapping" ) -> Sumatera Utara | M76: =IFERROR(__xludf.DUMMYFUNCTION("IF(REGEXMATCH(I76,""Cari Kerja""),1,0) "),0.0) -> 0 | N76: =IFERROR(__xludf.DUMMYFUNCTION("IF(REGEXMATCH(I76,""Upskill""),1,0) "),1.0) -> 1 | O76: =IFERROR(__xludf.DUMMYFUNCTION("IF(REGEXMATCH(I76,""Networking""),1,0) "),0.0) -> 0 | P76: =IFERROR(__xludf.DUMMYFUNCTION("IF(REGEXMATCH(I76,""Switch Career""),1,0) "),0.0) -> 0
A77: 46042.334 | B77: Andi nurfarhan assaq makumpelle | C77: andi11farhan@gmail.com | D77: 081818860803 | E77: Jakarta selatan | F77: Ya | G77: - | H77: Excel, SQL, Python, Power BI, Looker Studio, Databases, Tableau | I77: Cari Kerja, Upskill, Networking | J77: Instagram | K77: =IF(LEFT(D77,2)="62","0"&MID(D77,3,LEN(D77)),D77) -> 081818860803 | L77: =IFERROR( VLOOKUP( TRIM( IF(ISNUMBER(FIND(",",E77)), LEFT(E77,FIND(",",E77)-1), E77 ) ), master!A:B, 2, FALSE ), "Belum ada mapping" ) -> Jakarta | M77: =IFERROR(__xludf.DUMMYFUNCTION("IF(REGEXMATCH(I77,""Cari Kerja""),1,0) "),1.0) -> 1 | N77: =IFERROR(__xludf.DUMMYFUNCTION("IF(REGEXMATCH(I77,""Upskill""),1,0) "),1.0) -> 1 | O77: =IFERROR(__xludf.DUMMYFUNCTION("IF(REGEXMATCH(I77,""Networking""),1,0) "),1.0) -> 1 | P77: =IFERROR(__xludf.DUMMYFUNCTION("IF(REGEXMATCH(I77,""Switch Career""),1,0) "),0.0) -> 0
A78: 46040.347 | B78: Andi Riska Fitriani | C78: andiriskafitriani8@gmail.com | D78: 095190081964 | E78: Bulukumba | F78: Tidak | G78: IRT | H78: Excel, SQL, Python, Power BI, Tableau | I78: Cari Kerja | J78: Teman | K78: =IF(LEFT(D78,2)="62","0"&MID(D78,3,LEN(D78)),D78) -> 095190081964 | L78: =IFERROR( VLOOKUP( TRIM( IF(ISNUMBER(FIND(",",E78)), LEFT(E78,FIND(",",E78)-1), E78 ) ), master!A:B, 2, FALSE ), "Belum ada mapping" ) -> Sulawesi Selatan | M78: =IFERROR(__xludf.DUMMYFUNCTION("IF(REGEXMATCH(I78,""Cari Kerja""),1,0) "),1.0) -> 1 | N78: =IFERROR(__xludf.DUMMYFUNCTION("IF(REGEXMATCH(I78,""Upskill""),1,0) "),0.0) -> 0 | O78: =IFERROR(__xludf.DUMMYFUNCTION("IF(REGEXMATCH(I78,""Networking""),1,0) "),0.0) -> 0 | P78: =IFERROR(__xludf.DUMMYFUNCTION("IF(REGEXMATCH(I78,""Switch Career""),1,0) "),0.0) -> 0
A79: 46049.71 | B79: Andini Laviva Yana Ardita Wijaya | C79: andini.laviva.305@gmail.com | D79: 089612128105 | E79: Tulungagung | F79: Ya | G79: SCO JNE | H79: Excel, SQL, Python, Power BI, Looker Studio, Databases, Tableau | I79: Cari Kerja, Upskill, Networking | J79: LinkedIn | K79: =IF(LEFT(D79,2)="62","0"&MID(D79,3,LEN(D79)),D79) -> 089612128105 | L79: =IFERROR( VLOOKUP( TRIM( IF(ISNUMBER(FIND(",",E79)), LEFT(E79,FIND(",",E79)-1), E79 ) ), master!A:B, 2, FALSE ), "Belum ada mapping" ) -> Jawa Tengah | M79: =IFERROR(__xludf.DUMMYFUNCTION("IF(REGEXMATCH(I79,""Cari Kerja""),1,0) "),1.0) -> 1 | N79: =IFERROR(__xludf.DUMMYFUNCTION("IF(REGEXMATCH(I79,""Upskill""),1,0) "),1.0) -> 1 | O79: =IFERROR(__xludf.DUMMYFUNCTION("IF(REGEXMATCH(I79,""Networking""),1,0) "),1.0) -> 1 | P79: =IFERROR(__xludf.DUMMYFUNCTION("IF(REGEXMATCH(I79,""Switch Career""),1,0) "),0.0) -> 0
A80: 46041.824 | B80: Andreas Wahyu Kurniawan | C80: wahyukurniawan7374@gmail.com | D80: 082323403911 | E80: Yogyakarta | F80: Ya | G80: Wiraswasta | H80: Excel, SQL, Python, Power BI, Databases, Tableau | I80: Cari Kerja, Upskill, Networking | J80: LinkedIn | K80: =IF(LEFT(D80,2)="62","0"&MID(D80,3,LEN(D80)),D80) -> 082323403911 | L80: =IFERROR( VLOOKUP( TRIM( IF(ISNUMBER(FIND(",",E80)), LEFT(E80,FIND(",",E80)-1), E80 ) ), master!A:B, 2, FALSE ), "Belum ada mapping" ) -> DI Yogyakarta | M80: =IFERROR(__xludf.DUMMYFUNCTION("IF(REGEXMATCH(I80,""Cari Kerja""),1,0) "),1.0) -> 1 | N80: =IFERROR(__xludf.DUMMYFUNCTION("IF(REGEXMATCH(I80,""Upskill""),1,0) "),1.0) -> 1 | O80: =IFERROR(__xludf.DUMMYFUNCTION("IF(REGEXMATCH(I80,""Networking""),1,0) "),1.0) -> 1 | P80: =IFERROR(__xludf.DUMMYFUNCTION("IF(REGEXMATCH(I80,""Switch Career""),1,0) "),0.0) -> 0
A81: 46043.318 | B81: Andres Panchrista | C81: andrespanchrista@gmail.com | D81: 081318235417 | E81: Depok | F81: Tidak | G81: Project Management & NTi | H81: SQL, Python, Power BI, Looker Studio, Databases, Tableau | I81: Cari Kerja, Upskill, Networking | J81: LinkedIn | K81: =IF(LEFT(D81,2)="62","0"&MID(D81,3,LEN(D81)),D81) -> 081318235417 | L81: =IFERROR( VLOOKUP( TRIM( IF(ISNUMBER(FIND(",",E81)), LEFT(E81,FIND(",",E81)-1), E81 ) ), master!A:B, 2, FALSE ), "Belum ada mapping" ) -> Jawa Barat | M81: =IFERROR(__xludf.DUMMYFUNCTION("IF(REGEXMATCH(I81,""Cari Kerja""),1,0) "),1.0) -> 1 | N81: =IFERROR(__xludf.DUMMYFUNCTION("IF(REGEXMATCH(I81,""Upskill""),1,0) "),1.0) -> 1 | O81: =IFERROR(__xludf.DUMMYFUNCTION("IF(REGEXMATCH(I81,""Networking""),1,0) "),1.0) -> 1 | P81: =IFERROR(__xludf.DUMMYFUNCTION("IF(REGEXMATCH(I81,""Switch Career""),1,0) "),0.0) -> 0
A82: 46051.42 | B82: Andrie Mustika Rainy | C82: andrie.rainy@gmail.com | D82: 082112015376 | E82: Tanjung Enim, Sumatera Selatan | F82: Tidak | G82: Karyaean Swasta | H82: Excel, SQL, Python, Power BI, Looker Studio, Databases, Tableau | I82: Cari Kerja, Upskill, Networking, Switch Career | J82: Instagram | K82: =IF(LEFT(D82,2)="62","0"&MID(D82,3,LEN(D82)),D82) -> 082112015376 | L82: =IFERROR( VLOOKUP( TRIM( IF(ISNUMBER(FIND(",",E82)), LEFT(E82,FIND(",",E82)-1), E82 ) ), master!A:B, 2, FALSE ), "Belum ada mapping" ) -> Sumatera Selatan | M82: =IFERROR(__xludf.DUMMYFUNCTION("IF(REGEXMATCH(I82,""Cari Kerja""),1,0) "),1.0) -> 1 | N82: =IFERROR(__xludf.DUMMYFUNCTION("IF(REGEXMATCH(I82,""Upskill""),1,0) "),1.0) -> 1 | O82: =IFERROR(__xludf.DUMMYFUNCTION("IF(REGEXMATCH(I82,""Networking""),1,0) "),1.0) -> 1 | P82: =IFERROR(__xludf.DUMMYFUNCTION("IF(REGEXMATCH(I82,""Switch Career""),1,0) "),1.0) -> 1
A83: 46041.399 | B83: andy kristiyan ardianto | C83: kristblogspot@gmail.com | D83: 081347842174 | E83: sangatta | F83: Tidak | G83: maintenance instruktur , februari pindah jabatan menjadi maintenance planner | H83: Excel, Python, Power BI, Databases | I83: Upskill | J83: LinkedIn | K83: =IF(LEFT(D83,2)="62","0"&MID(D83,3,LEN(D83)),D83) -> 081347842174 | L83: =IFERROR( VLOOKUP( TRIM( IF(ISNUMBER(FIND(",",E83)), LEFT(E83,FIND(",",E83)-1), E83 ) ), master!A:B, 2, FALSE ), "Belum ada mapping" ) -> Kalimantan Timur | M83: =IFERROR(__xludf.DUMMYFUNCTION("IF(REGEXMATCH(I83,""Cari Kerja""),1,0) "),0.0) -> 0 | N83: =IFERROR(__xludf.DUMMYFUNCTION("IF(REGEXMATCH(I83,""Upskill""),1,0) "),1.0) -> 1 | O83: =IFERROR(__xludf.DUMMYFUNCTION("IF(REGEXMATCH(I83,""Networking""),1,0) "),0.0) -> 0 | P83: =IFERROR(__xludf.DUMMYFUNCTION("IF(REGEXMATCH(I83,""Switch Career""),1,0) "),0.0) -> 0
A84: 46040.355 | B84: Angelina Wardani | C84: angelinawardaa11@gmail.com | D84: 085755554957 | E84: Malang | F84: Ya | G84: Mahasiswa | H84: Excel, SQL, Python, Power BI, Databases | I84: Cari Kerja, Upskill | J84: LinkedIn | K84: =IF(LEFT(D84,2)="62","0"&MID(D84,3,LEN(D84)),D84) -> 085755554957 | L84: =IFERROR( VLOOKUP( TRIM( IF(ISNUMBER(FIND(",",E84)), LEFT(E84,FIND(",",E84)-1), E84 ) ), master!A:B, 2, FALSE ), "Belum ada mapping" ) -> Jawa Timur | M84: =IFERROR(__xludf.DUMMYFUNCTION("IF(REGEXMATCH(I84,""Cari Kerja""),1,0) "),1.0) -> 1 | N84: =IFERROR(__xludf.DUMMYFUNCTION("IF(REGEXMATCH(I84,""Upskill""),1,0) "),1.0) -> 1 | O84: =IFERROR(__xludf.DUMMYFUNCTION("IF(REGEXMATCH(I84,""Networking""),1,0) "),0.0) -> 0 | P84: =IFERROR(__xludf.DUMMYFUNCTION("IF(REGEXMATCH(I84,""Switch Career""),1,0) "),0.0) -> 0
A85: 46049.361 | B85: Anggelika Br Silaban | C85: anggelikasilaban06@gmail.com | D85: 081370899150 | E85: Jakarta Timur | F85: Ya | G85: Belum bekerja | H85: Excel, SQL, Python | I85: Cari Kerja, Upskill | J85: LinkedIn | K85: =IF(LEFT(D85,2)="62","0"&MID(D85,3,LEN(D85)),D85) -> 081370899150 | L85: =IFERROR( VLOOKUP( TRIM( IF(ISNUMBER(FIND(",",E85)), LEFT(E85,FIND(",",E85)-1), E85 ) ), master!A:B, 2, FALSE ), "Belum ada mapping" ) -> Jakarta | M85: =IFERROR(__xludf.DUMMYFUNCTION("IF(REGEXMATCH(I85,""Cari Kerja""),1,0) "),1.0) -> 1 | N85: =IFERROR(__xludf.DUMMYFUNCTION("IF(REGEXMATCH(I85,""Upskill""),1,0) "),1.0) -> 1 | O85: =IFERROR(__xludf.DUMMYFUNCTION("IF(REGEXMATCH(I85,""Networking""),1,0) "),0.0) -> 0 | P85: =IFERROR(__xludf.DUMMYFUNCTION("IF(REGEXMATCH(I85,""Switch Career""),1,0) "),0.0) -> 0
A86: 46040.354 | B86: Angger Zufan Hanggara | C86: anggerzhr@gmail.com | D86: 08887060286 | E86: Surakarta | F86: Ya | G86: Mahasiswa Universitas Sebelas Maret | H86: Excel, SQL, Python, Power BI, Tableau | I86: Upskill, Networking | J86: LinkedIn | K86: =IF(LEFT(D86,2)="62","0"&MID(D86,3,LEN(D86)),D86) -> 08887060286 | L86: =IFERROR( VLOOKUP( TRIM( IF(ISNUMBER(FIND(",",E86)), LEFT(E86,FIND(",",E86)-1), E86 ) ), master!A:B, 2, FALSE ), "Belum ada mapping" ) -> Jawa Tengah | M86: =IFERROR(__xludf.DUMMYFUNCTION("IF(REGEXMATCH(I86,""Cari Kerja""),1,0) "),0.0) -> 0 | N86: =IFERROR(__xludf.DUMMYFUNCTION("IF(REGEXMATCH(I86,""Upskill""),1,0) "),1.0) -> 1 | O86: =IFERROR(__xludf.DUMMYFUNCTION("IF(REGEXMATCH(I86,""Networking""),1,0) "),1.0) -> 1 | P86: =IFERROR(__xludf.DUMMYFUNCTION("IF(REGEXMATCH(I86,""Switch Career""),1,0) "),0.0) -> 0
A87: 46046.852 | B87: Anggi | C87: Angger | D87: 085158700150 | E87: Jakarta | F87: Tidak | G87: Logistik | H87: Excel, Looker Studio, Databases | I87: Switch Career | J87: Instagram | K87: =IF(LEFT(D87,2)="62","0"&MID(D87,3,LEN(D87)),D87) -> 085158700150 | L87: =IFERROR( VLOOKUP( TRIM( IF(ISNUMBER(FIND(",",E87)), LEFT(E87,FIND(",",E87)-1), E87 ) ), master!A:B, 2, FALSE ), "Belum ada mapping" ) -> Jakarta | M87: =IFERROR(__xludf.DUMMYFUNCTION("IF(REGEXMATCH(I87,""Cari Kerja""),1,0) "),0.0) -> 0 | N87: =IFERROR(__xludf.DUMMYFUNCTION("IF(REGEXMATCH(I87,""Upskill""),1,0) "),0.0) -> 0 | O87: =IFERROR(__xludf.DUMMYFUNCTION("IF(REGEXMATCH(I87,""Networking""),1,0) "),0.0) -> 0 | P87: =IFERROR(__xludf.DUMMYFUNCTION("IF(REGEXMATCH(I87,""Switch Career""),1,0) "),1.0) -> 1
A88: 46040.418 | B88: Anggi Riani Nurmudhi'ah | C88: anggirn03@gmail.com | D88: 082378235663 | E88: Palembang | F88: Tidak | G88: Jobseeker | H88: SQL, Python, Power BI, Looker Studio, Tableau | I88: Cari Kerja, Networking, Switch Career | J88: Instagram | K88: =IF(LEFT(D88,2)="62","0"&MID(D88,3,LEN(D88)),D88) -> 082378235663 | L88: =IFERROR( VLOOKUP( TRIM( IF(ISNUMBER(FIND(",",E88)), LEFT(E88,FIND(",",E88)-1), E88 ) ), master!A:B, 2, FALSE ), "Belum ada mapping" ) -> Sumatera Selatan | M88: =IFERROR(__xludf.DUMMYFUNCTION("IF(REGEXMATCH(I88,""Cari Kerja""),1,0) "),1.0) -> 1 | N88: =IFERROR(__xludf.DUMMYFUNCTION("IF(REGEXMATCH(I88,""Upskill""),1,0) "),0.0) -> 0 | O88: =IFERROR(__xludf.DUMMYFUNCTION("IF(REGEXMATCH(I88,""Networking""),1,0) "),1.0) -> 1 | P88: =IFERROR(__xludf.DUMMYFUNCTION("IF(REGEXMATCH(I88,""Switch Career""),1,0) "),1.0) -> 1
A89: 46044.987 | B89: Anggita Anastya | C89: anggitaanastya83@gmail.com | D89: 089611357078 | E89: Lampung | F89: Ya | G89: - | H89: Excel, SQL, Python, Power BI, Looker Studio, Databases, Tableau | I89: Cari Kerja, Upskill, Networking | J89: LinkedIn | K89: =IF(LEFT(D89,2)="62","0"&MID(D89,3,LEN(D89)),D89) -> 089611357078 | L89: =IFERROR( VLOOKUP( TRIM( IF(ISNUMBER(FIND(",",E89)), LEFT(E89,FIND(",",E89)-1), E89 ) ), master!A:B, 2, FALSE ), "Belum ada mapping" ) -> Lampung | M89: =IFERROR(__xludf.DUMMYFUNCTION("IF(REGEXMATCH(I89,""Cari Kerja""),1,0) "),1.0) -> 1 | N89: =IFERROR(__xludf.DUMMYFUNCTION("IF(REGEXMATCH(I89,""Upskill""),1,0) "),1.0) -> 1 | O89: =IFERROR(__xludf.DUMMYFUNCTION("IF(REGEXMATCH(I89,""Networking""),1,0) "),1.0) -> 1 | P89: =IFERROR(__xludf.DUMMYFUNCTION("IF(REGEXMATCH(I89,""Switch Career""),1,0) "),0.0) -> 0
A90: 46047.937 | B90: Anggreta Sela Indriaputri | C90: anggretasela123@gmail.com | D90: 0895327074221 | E90: DKI Jakarta | F90: Ya | G90: Technical Support - PLN ICONPLUS | H90: SQL, Python, Power BI, Tableau | I90: Upskill, Networking, Switch Career | J90: LinkedIn | K90: =IF(LEFT(D90,2)="62","0"&MID(D90,3,LEN(D90)),D90) -> 0895327074221 | L90: =IFERROR( VLOOKUP( TRIM( IF(ISNUMBER(FIND(",",E90)), LEFT(E90,FIND(",",E90)-1), E90 ) ), master!A:B, 2, FALSE ), "Belum ada mapping" ) -> Jakarta | M90: =IFERROR(__xludf.DUMMYFUNCTION("IF(REGEXMATCH(I90,""Cari Kerja""),1,0) "),0.0) -> 0 | N90: =IFERROR(__xludf.DUMMYFUNCTION("IF(REGEXMATCH(I90,""Upskill""),1,0) "),1.0) -> 1 | O90: =IFERROR(__xludf.DUMMYFUNCTION("IF(REGEXMATCH(I90,""Networking""),1,0) "),1.0) -> 1 | P90: =IFERROR(__xludf.DUMMYFUNCTION("IF(REGEXMATCH(I90,""Switch Career""),1,0) "),1.0) -> 1
A91: 46045.873 | B91: Aninda Syifa Rosita Uyun | C91: anindasyifarositauyun@gmail.com | D91: 08569022344 | E91: Kudus | F91: Tidak | G91: PT HWI | H91: Excel, SQL, Python, Power BI, Looker Studio, Databases, Tableau | I91: Cari Kerja, Upskill, Networking, Switch Career | J91: LinkedIn | K91: =IF(LEFT(D91,2)="62","0"&MID(D91,3,LEN(D91)),D91) -> 08569022344 | L91: =IFERROR( VLOOKUP( TRIM( IF(ISNUMBER(FIND(",",E91)), LEFT(E91,FIND(",",E91)-1), E91 ) ), master!A:B, 2, FALSE ), "Belum ada mapping" ) -> Jawa Tengah | M91: =IFERROR(__xludf.DUMMYFUNCTION("IF(REGEXMATCH(I91,""Cari Kerja""),1,0) "),1.0) -> 1 | N91: =IFERROR(__xludf.DUMMYFUNCTION("IF(REGEXMATCH(I91,""Upskill""),1,0) "),1.0) -> 1 | O91: =IFERROR(__xludf.DUMMYFUNCTION("IF(REGEXMATCH(I91,""Networking""),1,0) "),1.0) -> 1 | P91: =IFERROR(__xludf.DUMMYFUNCTION("IF(REGEXMATCH(I91,""Switch Career""),1,0) "),1.0) -> 1
A92: 46043.263 | B92: Anis Merida Nasywa | C92: anasywa76@gmail.com | D92: 085142427956 | E92: Malang, Jawa Timur | F92: Ya | G92: Mahasiswa di UIN Maulana Malik Ibrahim Malang | H92: Excel, SQL, Python, Power BI, Looker Studio, Databases, Tableau | I92: Cari Kerja, Upskill, Networking | J92: Teman | K92: =IF(LEFT(D92,2)="62","0"&MID(D92,3,LEN(D92)),D92) -> 085142427956 | L92: =IFERROR( VLOOKUP( TRIM( IF(ISNUMBER(FIND(",",E92)), LEFT(E92,FIND(",",E92)-1), E92 ) ), master!A:B, 2, FALSE ), "Belum ada mapping" ) -> Jawa Timur | M92: =IFERROR(__xludf.DUMMYFUNCTION("IF(REGEXMATCH(I92,""Cari Kerja""),1,0) "),1.0) -> 1 | N92: =IFERROR(__xludf.DUMMYFUNCTION("IF(REGEXMATCH(I92,""Upskill""),1,0) "),1.0) -> 1 | O92: =IFERROR(__xludf.DUMMYFUNCTION("IF(REGEXMATCH(I92,""Networking""),1,0) "),1.0) -> 1 | P92: =IFERROR(__xludf.DUMMYFUNCTION("IF(REGEXMATCH(I92,""Switch Career""),1,0) "),0.0) -> 0
A93: 46043.331 | B93: Anisa Nur Fitri | C93: anisanurfitri300@gmail.com | D93: 082282110287 | E93: Jakarta Selatan | F93: Ya | G93: Magang di Kementrian Pertanian | H93: Excel, SQL, Python, Power BI, Looker Studio, Databases, Tableau | I93: Cari Kerja, Upskill | J93: LinkedIn | K93: =IF(LEFT(D93,2)="62","0"&MID(D93,3,LEN(D93)),D93) -> 082282110287 | L93: =IFERROR( VLOOKUP( TRIM( IF(ISNUMBER(FIND(",",E93)), LEFT(E93,FIND(",",E93)-1), E93 ) ), master!A:B, 2, FALSE ), "Belum ada mapping" ) -> Jakarta | M93: =IFERROR(__xludf.DUMMYFUNCTION("IF(REGEXMATCH(I93,""Cari Kerja""),1,0) "),1.0) -> 1 | N93: =IFERROR(__xludf.DUMMYFUNCTION("IF(REGEXMATCH(I93,""Upskill""),1,0) "),1.0) -> 1 | O93: =IFERROR(__xludf.DUMMYFUNCTION("IF(REGEXMATCH(I93,""Networking""),1,0) "),0.0) -> 0 | P93: =IFERROR(__xludf.DUMMYFUNCTION("IF(REGEXMATCH(I93,""Switch Career""),1,0) "),0.0) -> 0
A94: 46046.4 | B94: Anisa Rosdiana | C94: anisaros03@gmail.com | D94: 082123932790 | E94: Tangerang | F94: Ya | G94: Supply Chain Management Officer | H94: Excel, Python, Power BI, Databases | I94: Upskill, Networking | J94: Instagram | K94: =IF(LEFT(D94,2)="62","0"&MID(D94,3,LEN(D94)),D94) -> 082123932790 | L94: =IFERROR( VLOOKUP( TRIM( IF(ISNUMBER(FIND(",",E94)), LEFT(E94,FIND(",",E94)-1), E94 ) ), master!A:B, 2, FALSE ), "Belum ada mapping" ) -> Banten | M94: =IFERROR(__xludf.DUMMYFUNCTION("IF(REGEXMATCH(I94,""Cari Kerja""),1,0) "),0.0) -> 0 | N94: =IFERROR(__xludf.DUMMYFUNCTION("IF(REGEXMATCH(I94,""Upskill""),1,0) "),1.0) -> 1 | O94: =IFERROR(__xludf.DUMMYFUNCTION("IF(REGEXMATCH(I94,""Networking""),1,0) "),1.0) -> 1 | P94: =IFERROR(__xludf.DUMMYFUNCTION("IF(REGEXMATCH(I94,""Switch Career""),1,0) "),0.0) -> 0
A95: 46043.389 | B95: Anjas Roy Rizki | C95: anjasrisk25@gmail.com | D95: 089618467388 | E95: Semarang | F95: Ya | G95: Unnisula | H95: Excel, SQL, Python, Power BI, Looker Studio, Databases, Tableau | I95: Cari Kerja, Upskill, Networking | J95: Teman | K95: =IF(LEFT(D95,2)="62","0"&MID(D95,3,LEN(D95)),D95) -> 089618467388 | L95: =IFERROR( VLOOKUP( TRIM( IF(ISNUMBER(FIND(",",E95)), LEFT(E95,FIND(",",E95)-1), E95 ) ), master!A:B, 2, FALSE ), "Belum ada mapping" ) -> Jawa Tengah | M95: =IFERROR(__xludf.DUMMYFUNCTION("IF(REGEXMATCH(I95,""Cari Kerja""),1,0) "),1.0) -> 1 | N95: =IFERROR(__xludf.DUMMYFUNCTION("IF(REGEXMATCH(I95,""Upskill""),1,0) "),1.0) -> 1 | O95: =IFERROR(__xludf.DUMMYFUNCTION("IF(REGEXMATCH(I95,""Networking""),1,0) "),1.0) -> 1 | P95: =IFERROR(__xludf.DUMMYFUNCTION("IF(REGEXMATCH(I95,""Switch Career""),1,0) "),0.0) -> 0
A96: 46042.302 | B96: Annida Syamsa Hawa | C96: annidasyamsa2@gmail.com | D96: 089516719920 | E96: Banyumas | F96: Ya | G96: Mahasiswa | H96: Excel, SQL, Python, Power BI, Looker Studio, Databases, Tableau | I96: Cari Kerja, Upskill, Networking | J96: LinkedIn | K96: =IF(LEFT(D96,2)="62","0"&MID(D96,3,LEN(D96)),D96) -> 089516719920 | L96: =IFERROR( VLOOKUP( TRIM( IF(ISNUMBER(FIND(",",E96)), LEFT(E96,FIND(",",E96)-1), E96 ) ), master!A:B, 2, FALSE ), "Belum ada mapping" ) -> Jawa Tengah | M96: =IFERROR(__xludf.DUMMYFUNCTION("IF(REGEXMATCH(I96,""Cari Kerja""),1,0) "),1.0) -> 1 | N96: =IFERROR(__xludf.DUMMYFUNCTION("IF(REGEXMATCH(I96,""Upskill""),1,0) "),1.0) -> 1 | O96: =IFERROR(__xludf.DUMMYFUNCTION("IF(REGEXMATCH(I96,""Networking""),1,0) "),1.0) -> 1 | P96: =IFERROR(__xludf.DUMMYFUNCTION("IF(REGEXMATCH(I96,""Switch Career""),1,0) "),0.0) -> 0
A97: 46040.357 | B97: Annisa Helly Suranda | C97: nisahelly15@gmail.com | D97: 081539356952 | E97: Bengkulu | F97: Tidak | G97: - | H97: Excel, SQL, Python | I97: Upskill, Switch Career | J97: LinkedIn | K97: =IF(LEFT(D97,2)="62","0"&MID(D97,3,LEN(D97)),D97) -> 081539356952 | L97: =IFERROR( VLOOKUP( TRIM( IF(ISNUMBER(FIND(",",E97)), LEFT(E97,FIND(",",E97)-1), E97 ) ), master!A:B, 2, FALSE ), "Belum ada mapping" ) -> Bengkulu | M97: =IFERROR(__xludf.DUMMYFUNCTION("IF(REGEXMATCH(I97,""Cari Kerja""),1,0) "),0.0) -> 0 | N97: =IFERROR(__xludf.DUMMYFUNCTION("IF(REGEXMATCH(I97,""Upskill""),1,0) "),1.0) -> 1 | O97: =IFERROR(__xludf.DUMMYFUNCTION("IF(REGEXMATCH(I97,""Networking""),1,0) "),0.0) -> 0 | P97: =IFERROR(__xludf.DUMMYFUNCTION("IF(REGEXMATCH(I97,""Switch Career""),1,0) "),1.0) -> 1
A98: 46042.367 | B98: Annisa Larasati | C98: annisalarasati.all@gmail.com | D98: 089601630666 | E98: Tangerang | F98: Tidak | G98: Accounting Staff | H98: Excel, SQL, Python, Looker Studio | I98: Upskill, Switch Career | J98: LinkedIn | K98: =IF(LEFT(D98,2)="62","0"&MID(D98,3,LEN(D98)),D98) -> 089601630666 | L98: =IFERROR( VLOOKUP( TRIM( IF(ISNUMBER(FIND(",",E98)), LEFT(E98,FIND(",",E98)-1), E98 ) ), master!A:B, 2, FALSE ), "Belum ada mapping" ) -> Banten | M98: =IFERROR(__xludf.DUMMYFUNCTION("IF(REGEXMATCH(I98,""Cari Kerja""),1,0) "),0.0) -> 0 | N98: =IFERROR(__xludf.DUMMYFUNCTION("IF(REGEXMATCH(I98,""Upskill""),1,0) "),1.0) -> 1 | O98: =IFERROR(__xludf.DUMMYFUNCTION("IF(REGEXMATCH(I98,""Networking""),1,0) "),0.0) -> 0 | P98: =IFERROR(__xludf.DUMMYFUNCTION("IF(REGEXMATCH(I98,""Switch Career""),1,0) "),1.0) -> 1
A99: 46047.367 | B99: Annisa Novantika | C99: annisanovantika.a@gmail.com | D99: 082278822285 | E99: Lampung | F99: Ya | G99: Magang - KPPN Liwa | H99: SQL, Python, Power BI, Tableau | I99: Cari Kerja, Upskill | J99: LinkedIn | K99: =IF(LEFT(D99,2)="62","0"&MID(D99,3,LEN(D99)),D99) -> 082278822285 | L99: =IFERROR( VLOOKUP( TRIM( IF(ISNUMBER(FIND(",",E99)), LEFT(E99,FIND(",",E99)-1), E99 ) ), master!A:B, 2, FALSE ), "Belum ada mapping" ) -> Lampung | M99: =IFERROR(__xludf.DUMMYFUNCTION("IF(REGEXMATCH(I99,""Cari Kerja""),1,0) "),1.0) -> 1 | N99: =IFERROR(__xludf.DUMMYFUNCTION("IF(REGEXMATCH(I99,""Upskill""),1,0) "),1.0) -> 1 | O99: =IFERROR(__xludf.DUMMYFUNCTION("IF(REGEXMATCH(I99,""Networking""),1,0) "),0.0) -> 0 | P99: =IFERROR(__xludf.DUMMYFUNCTION("IF(REGEXMATCH(I99,""Switch Career""),1,0) "),0.0) -> 0
A100: 46040.462 | B100: Anson | C100: ansonkm123@gmail.com | D100: 082390283788 | E100: Batam | F100: Ya | G100: - | H100: Excel, SQL, Python, Power BI, Tableau | I100: Cari Kerja, Networking | J100: Instagram | K100: =IF(LEFT(D100,2)="62","0"&MID(D100,3,LEN(D100)),D100) -> 082390283788 | L100: =IFERROR( VLOOKUP( TRIM( IF(ISNUMBER(FIND(",",E100)), LEFT(E100,FIND(",",E100)-1), E100 ) ), master!A:B, 2, FALSE ), "Belum ada mapping" ) -> Riau | M100: =IFERROR(__xludf.DUMMYFUNCTION("IF(REGEXMATCH(I100,""Cari Kerja""),1,0) "),1.0) -> 1 | N100: =IFERROR(__xludf.DUMMYFUNCTION("IF(REGEXMATCH(I100,""Upskill""),1,0) "),0.0) -> 0 | O100: =IFERROR(__xludf.DUMMYFUNCTION("IF(REGEXMATCH(I100,""Networking""),1,0) "),1.0) -> 1 | P100: =IFERROR(__xludf.DUMMYFUNCTION("IF(REGEXMATCH(I100,""Switch Career""),1,0) "),0.0) -> 0
...

Sheet master
A1: Domisili | B1: Provinsi
A2: Aceh | B2: Aceh
A3: Aceh Utara | B3: Aceh
A4: Denpasar | B4: Bali
A5: Belitung | B5: Bangka Belitung
A6: Banten | B6: Banten
A7: BSD | B7: Banten
A8: Cilegon | B8: Banten
A9: Kab. Tangerang | B9: Banten
A10: Pamulang | B10: Banten
A11: Rangkasbitung | B11: Banten
A12: Serang | B12: Banten
... A146: Sumatra Selatan | B146: Sumatra Selatan

Sheet dataset
A1: id | B1: {='Form Responses 1'!E:J} -> Domisili | C1: Apakah Anda Mahasiswa / Fresh Graduate | D1: Pekerjaan & Instansi Saat Ini | E1: Tools yang Ingin Dipelajari | F1: Target Join Komunitas | G1: Tau Seara Data Dari Mana? | H1: Provinsi | I1: Cari Kerja
A2: 1 | B2: Jawa Tengah | C2: Ya | D2: Mahasiswa | E2: Python, Tableau | F2: Cari Kerja, Upskill, Networking | G2: LinkedIn | H2: =IFERROR(VLOOKUP(TRIM(IF(ISNUMBER(FIND(",", B2)),LEFT(B2,FIND(",",B2)-1),B2)),master!A:B,2,FALSE),"Belum ada mapping") -> Jawa Tengah | I2: =IFERROR(__xludf.DUMMYFUNCTION("IF(REGEXMATCH(F2,""Cari Kerja""),1,0)"),1.0) -> 1
A3: 2 | B3: Padang | C3: Ya | D3: belum ada | E3: Excel, SQL, Python, Power BI | F3: Cari Kerja, Upskill, Networking, Switch Career | G3: LinkedIn | H3: =IFERROR(VLOOKUP(TRIM(IF(ISNUMBER(FIND(",", B3)),LEFT(B3,FIND(",",B3)-1),B3)),master!A:B,2,FALSE),"Belum ada mapping") -> Sumatera Barat | I3: =IFERROR(__xludf.DUMMYFUNCTION("IF(REGEXMATCH(F3,""Cari Kerja""),1,0)"),1.0) -> 1
A4: 3 | B4: Surabaya | C4: Ya | D4: Freelance Web Development | E4: Excel, SQL, Python, Power BI, Databases | F4: Cari Kerja, Upskill, Networking | G4: Teman | H4: =IFERROR(VLOOKUP(TRIM(IF(ISNUMBER(FIND(",", B4)),LEFT(B4,FIND(",",B4)-1),B4)),master!A:B,2,FALSE),"Belum ada mapping") -> Jawa Timur | I4: =IFERROR(__xludf.DUMMYFUNCTION("IF(REGEXMATCH(F4,""Cari Kerja""),1,0)"),1.0) -> 1
A5: 4 | B5: Bandung | C5: Ya | D5: Konsultan Perencanaan Kota | E5: Python, Power BI | F5: Upskill | G5: LinkedIn | H5: =IFERROR(VLOOKUP(TRIM(IF(ISNUMBER(FIND(",", B5)),LEFT(B5,FIND(",",B5)-1),B5)),master!A:B,2,FALSE),"Belum ada mapping") -> Jawa Barat | I5: =IFERROR(__xludf.DUMMYFUNCTION("IF(REGEXMATCH(F5,""Cari Kerja""),1,0)"),0.0) -> 0
A6: 5 | B6: Yogyakarta | C6: Tidak | D6: Senior Barista _- Esha kopi | E6: Excel, SQL, Python, Power BI, Looker Studio, Databases, Tableau | F6: Upskill, Networking, Switch Career | G6: Teman | H6: =IFERROR(VLOOKUP(TRIM(IF(ISNUMBER(FIND(",", B6)),LEFT(B6,FIND(",",B6)-1),B6)),master!A:B,2,FALSE),"Belum ada mapping") -> DI Yogyakarta | I6: =IFERROR(__xludf.DUMMYFUNCTION("IF(REGEXMATCH(F6,""Cari Kerja""),1,0)"),0.0) -> 0
A7: 6 | B7: Tangerang | C7: Ya | D7: Data & Informasi System Staff, Kementerian Desa PDT | E7: Excel, SQL, Power BI, Tableau | F7: Upskill, Networking | G7: Teman | H7: =IFERROR(VLOOKUP(TRIM(IF(ISNUMBER(FIND(",", B7)),LEFT(B7,FIND(",",B7)-1),B7)),master!A:B,2,FALSE),"Belum ada mapping") -> Banten | I7: =IFERROR(__xludf.DUMMYFUNCTION("IF(REGEXMATCH(F7,""Cari Kerja""),1,0)"),0.0) -> 0
A8: 7 | B8: Kudus | C8: Tidak | D8: Admin Personalia | E8: Excel, SQL, Python, Power BI, Looker Studio, Databases, Tableau | F8: Cari Kerja, Upskill, Networking, Switch Career | G8: LinkedIn | H8: =IFERROR(VLOOKUP(TRIM(IF(ISNUMBER(FIND(",", B8)),LEFT(B8,FIND(",",B8)-1),B8)),master!A:B,2,FALSE),"Belum ada mapping") -> Jawa Tengah | I8: =IFERROR(__xludf.DUMMYFUNCTION("IF(REGEXMATCH(F8,""Cari Kerja""),1,0)"),1.0) -> 1
A9: 8 | B9: Boyolali | C9: Ya | D9: - | E9: Excel, SQL, Python, Power BI, Looker Studio, Databases, Airflow | F9: Cari Kerja, Upskill, Networking | G9: LinkedIn | H9: =IFERROR(VLOOKUP(TRIM(IF(ISNUMBER(FIND(",", B9)),LEFT(B9,FIND(",",B9)-1),B9)),master!A:B,2,FALSE),"Belum ada mapping") -> Jawa Tengah | I9: =IFERROR(__xludf.DUMMYFUNCTION("IF(REGEXMATCH(F9,""Cari Kerja""),1,0)"),1.0) -> 1
A10: 9 | B10: Tangerang | C10: Tidak | D10: Senior Business Intelegence Dekoruma | E10: Excel, SQL, Python, Power BI, Looker Studio, Databases, Tableau | F10: Upskill, Networking | G10: Instagram | H10: =IFERROR(VLOOKUP(TRIM(IF(ISNUMBER(FIND(",", B10)),LEFT(B10,FIND(",",B10)-1),B10)),master!A:B,2,FALSE),"Belum ada mapping") -> Banten | I10: =IFERROR(__xludf.DUMMYFUNCTION("IF(REGEXMATCH(F10,""Cari Kerja""),1,0)"),0.0) -> 0
A11: 10 | B11: Sidoarjo, Jawa Timur | C11: Tidak | D11: Audit - PT Jawa Berkat Indonesia | E11: Excel, SQL, Python, Power BI, Looker Studio, Tableau | F11: Cari Kerja, Upskill, Networking, Switch Career | G11: Teman | H11: =IFERROR(VLOOKUP(TRIM(IF(ISNUMBER(FIND(",", B11)),LEFT(B11,FIND(",",B11)-1),B11)),master!A:B,2,FALSE),"Belum ada mapping") -> Jawa Timur | I11: =IFERROR(__xludf.DUMMYFUNCTION("IF(REGEXMATCH(F11,""Cari Kerja""),1,0)"),1.0) -> 1
A12: 11 | B12: Banyumas | C12: Ya | D12: - | E12: Excel, SQL, Python, Power BI, Looker Studio, Databases | F12: Cari Kerja | G12: Instagram | H12: =IFERROR(VLOOKUP(TRIM(IF(ISNUMBER(FIND(",", B12)),LEFT(B12,FIND(",",B12)-1),B12)),master!A:B,2,FALSE),"Belum ada mapping") -> Jawa Tengah | I12: =IFERROR(__xludf.DUMMYFUNCTION("IF(REGEXMATCH(F12,""Cari Kerja""),1,0)"),1.0) -> 1
A13: 12 | B13: Jawa Tengah | C13: Ya | D13: - | E13: Excel, SQL, Python, Power BI, Looker Studio, Databases, Tableau | F13: Cari Kerja, Upskill, Networking | G13: LinkedIn | H13: =IFERROR(VLOOKUP(TRIM(IF(ISNUMBER(FIND(",", B13)),LEFT(B13,FIND(",",B13)-1),B13)),master!A:B,2,FALSE),"Belum ada mapping") -> Jawa Tengah | I13: =IFERROR(__xludf.DUMMYFUNCTION("IF(REGEXMATCH(F13,""Cari Kerja""),1,0)"),1.0) -> 1
A14: 13 | B14: Bekasi | C14: Ya | D14: - | E14: Excel, SQL, Python, Power BI, Tableau | F14: Upskill | G14: Teman | H14: =IFERROR(VLOOKUP(TRIM(IF(ISNUMBER(FIND(",", B14)),LEFT(B14,FIND(",",B14)-1),B14)),master!A:B,2,FALSE),"Belum ada mapping") -> Jawa Barat | I14: =IFERROR(__xludf.DUMMYFUNCTION("IF(REGEXMATCH(F14,""Cari Kerja""),1,0)"),0.0) -> 0
A15: 14 | B15: Jakarta Timur | C15: Tidak | D15: Warehouse - Supply Chain | E15: Excel, SQL, Python, Power BI | F15: Upskill, Networking | G15: LinkedIn | H15: =IFERROR(VLOOKUP(TRIM(IF(ISNUMBER(FIND(",", B15)),LEFT(B15,FIND(",",B15)-1),B15)),master!A:B,2,FALSE),"Belum ada mapping") -> Jakarta | I15: =IFERROR(__xludf.DUMMYFUNCTION("IF(REGEXMATCH(F15,""Cari Kerja""),1,0)"),0.0) -> 0
A16: 15 | B16: Padang | C16: Tidak | D16: ASN | E16: Excel, SQL, Python, Power BI, Looker Studio, Databases, Tableau, Anything | F16: Cari Kerja, Upskill, Networking, Switch Career | G16: LinkedIn | H16: =IFERROR(VLOOKUP(TRIM(IF(ISNUMBER(FIND(",", B16)),LEFT(B16,FIND(",",B16)-1),B16)),master!A:B,2,FALSE),"Belum ada mapping") -> Sumatera Barat | I16: =IFERROR(__xludf.DUMMYFUNCTION("IF(REGEXMATCH(F16,""Cari Kerja""),1,0)"),1.0) -> 1
A17: 16 | B17: Cianjur | C17: Tidak | D17: Staff HR di salah satu Bank Swasta | E17: Excel, SQL, Python, Power BI, Databases | F17: Cari Kerja, Networking | G17: Teman | H17: =IFERROR(VLOOKUP(TRIM(IF(ISNUMBER(FIND(",", B17)),LEFT(B17,FIND(",",B17)-1),B17)),master!A:B,2,FALSE),"Belum ada mapping") -> Jawa Barat | I17: =IFERROR(__xludf.DUMMYFUNCTION("IF(REGEXMATCH(F17,""Cari Kerja""),1,0)"),1.0) -> 1
A18: 17 | B18: Medan | C18: Tidak | D18: Idle | E18: Excel, SQL, Python, Power BI, Looker Studio, Databases, Tableau | F18: Cari Kerja, Upskill, Networking, Switch Career | G18: LinkedIn | H18: =IFERROR(VLOOKUP(TRIM(IF(ISNUMBER(FIND(",", B18)),LEFT(B18,FIND(",",B18)-1),B18)),master!A:B,2,FALSE),"Belum ada mapping") -> Sumatera Utara | I18: =IFERROR(__xludf.DUMMYFUNCTION("IF(REGEXMATCH(F18,""Cari Kerja""),1,0)"),1.0) -> 1
A19: 18 | B19: Gresik | C19: Ya | D19: Mahasiswa | E19: Excel, SQL, Python, Power BI, Tableau | F19: Cari Kerja, Upskill, Networking | G19: LinkedIn | H19: =IFERROR(VLOOKUP(TRIM(IF(ISNUMBER(FIND(",", B19)),LEFT(B19,FIND(",",B19)-1),B19)),master!A:B,2,FALSE),"Belum ada mapping") -> Jawa Timur | I19: =IFERROR(__xludf.DUMMYFUNCTION("IF(REGEXMATCH(F19,""Cari Kerja""),1,0)"),1.0) -> 1
A20: 19 | B20: Makassar | C20: Ya | D20: Quality System Intern | E20: Excel, SQL, Python, Power BI, Looker Studio, Databases, Tableau | F20: Cari Kerja, Upskill, Networking | G20: LinkedIn | H20: =IFERROR(VLOOKUP(TRIM(IF(ISNUMBER(FIND(",", B20)),LEFT(B20,FIND(",",B20)-1),B20)),master!A:B,2,FALSE),"Belum ada mapping") -> Sulawesi Selatan | I20: =IFERROR(__xludf.DUMMYFUNCTION("IF(REGEXMATCH(F20,""Cari Kerja""),1,0)"),1.0) -> 1
A21: 20 | B21: Jawa Barat, | C21: Ya | D21: Freshgraduated | E21: Excel, SQL, Power BI, Looker Studio | F21: Cari Kerja, Upskill | G21: LinkedIn | H21: =IFERROR(VLOOKUP(TRIM(IF(ISNUMBER(FIND(",", B21)),LEFT(B21,FIND(",",B21)-1),B21)),master!A:B,2,FALSE),"Belum ada mapping") -> Jawa Barat | I21: =IFERROR(__xludf.DUMMYFUNCTION("IF(REGEXMATCH(F21,""Cari Kerja""),1,0)"),1.0) -> 1
A22: 21 | B22: Bandung | C22: Ya | D22: Magang - Pemerintahan (BBPMP Jabar) | E22: Power BI, Looker Studio, Tableau | F22: Cari Kerja, Upskill | G22: LinkedIn | H22: =IFERROR(VLOOKUP(TRIM(IF(ISNUMBER(FIND(",", B22)),LEFT(B22,FIND(",",B22)-1),B22)),master!A:B,2,FALSE),"Belum ada mapping") -> Jawa Barat | I22: =IFERROR(__xludf.DUMMYFUNCTION("IF(REGEXMATCH(F22,""Cari Kerja""),1,0)"),1.0) -> 1
A23: 22 | B23: Bekasi | C23: Tidak | D23: PT SOKKA TAMA FIBER | E23: Excel, SQL, Python, Power BI, Looker Studio, Databases, Tableau | F23: Upskill, Networking, Switch Career | G23: Instagram | H23: =IFERROR(VLOOKUP(TRIM(IF(ISNUMBER(FIND(",", B23)),LEFT(B23,FIND(",",B23)-1),B23)),master!A:B,2,FALSE),"Belum ada mapping") -> Jawa Barat | I23: =IFERROR(__xludf.DUMMYFUNCTION("IF(REGEXMATCH(F23,""Cari Kerja""),1,0)"),0.0) -> 0
A24: 23 | B24: Tangerang | C24: Ya | D24: Student | E24: Excel, SQL, Python, Power BI, Looker Studio, Databases, Tableau | F24: Upskill, Networking | G24: LinkedIn | H24: =IFERROR(VLOOKUP(TRIM(IF(ISNUMBER(FIND(",", B24)),LEFT(B24,FIND(",",B24)-1),B24)),master!A:B,2,FALSE),"Belum ada mapping") -> Banten | I24: =IFERROR(__xludf.DUMMYFUNCTION("IF(REGEXMATCH(F24,""Cari Kerja""),1,0)"),0.0) -> 0
A25: 24 | B25: Dumai | C25: Tidak | D25: Freelance | E25: Excel, SQL, Python, Power BI, Tableau | F25: Upskill | G25: LinkedIn | H25: =IFERROR(VLOOKUP(TRIM(IF(ISNUMBER(FIND(",", B25)),LEFT(B25,FIND(",",B25)-1),B25)),master!A:B,2,FALSE),"Belum ada mapping") -> Riau | I25: =IFERROR(__xludf.DUMMYFUNCTION("IF(REGEXMATCH(F25,""Cari Kerja""),1,0)"),0.0) -> 0
A26: 25 | B26: Dumai | C26: Tidak | D26: Freelance | E26: Excel, SQL, Python, Power BI, Tableau | F26: Upskill | G26: LinkedIn | H26: =IFERROR(VLOOKUP(TRIM(IF(ISNUMBER(FIND(",", B26)),LEFT(B26,FIND(",",B26)-1),B26)),master!A:B,2,FALSE),"Belum ada mapping") -> Riau | I26: =IFERROR(__xludf.DUMMYFUNCTION("IF(REGEXMATCH(F26,""Cari Kerja""),1,0)"),0.0) -> 0
A27: 26 | B27: Pekanbaru | C27: Tidak | D27: Un employee | E27: Excel, Python, Power BI | F27: Upskill, Switch Career | G27: LinkedIn | H27: =IFERROR(VLOOKUP(TRIM(IF(ISNUMBER(FIND(",", B27)),LEFT(B27,FIND(",",B27)-1),B27)),master!A:B,2,FALSE),"Belum ada mapping") -> Riau | I27: =IFERROR(__xludf.DUMMYFUNCTION("IF(REGEXMATCH(F27,""Cari Kerja""),1,0)"),0.0) -> 0
A28: 27 | B28: Depok | C28: Ya | D28: Politeknik Negeri Jakarta | E28: Excel, SQL, Python, Power BI, Looker Studio | F28: Cari Kerja, Upskill, Networking, Switch Career | G28: LinkedIn | H28: =IFERROR(VLOOKUP(TRIM(IF(ISNUMBER(FIND(",", B28)),LEFT(B28,FIND(",",B28)-1),B28)),master!A:B,2,FALSE),"Belum ada mapping") -> Jawa Barat | I28: =IFERROR(__xludf.DUMMYFUNCTION("IF(REGEXMATCH(F28,""Cari Kerja""),1,0)"),1.0) -> 1
A29: 28 | B29: Purworejo | C29: Ya | D29: - | E29: Excel, SQL, Python, Looker Studio | F29: Cari Kerja, Upskill, Networking | G29: LinkedIn | H29: =IFERROR(VLOOKUP(TRIM(IF(ISNUMBER(FIND(",", B29)),LEFT(B29,FIND(",",B29)-1),B29)),master!A:B,2,FALSE),"Belum ada mapping") -> Jawa Tengah | I29: =IFERROR(__xludf.DUMMYFUNCTION("IF(REGEXMATCH(F29,""Cari Kerja""),1,0)"),1.0) -> 1
A30: 29 | B30: Medan | C30: Ya | D30: Tidak ada | E30: SQL, Python, Power BI, Looker Studio, Tableau | F30: Cari Kerja | G30: LinkedIn | H30: =IFERROR(VLOOKUP(TRIM(IF(ISNUMBER(FIND(",", B30)),LEFT(B30,FIND(",",B30)-1),B30)),master!A:B,2,FALSE),"Belum ada mapping") -> Sumatera Utara | I30: =IFERROR(__xludf.DUMMYFUNCTION("IF(REGEXMATCH(F30,""Cari Kerja""),1,0)"),1.0) -> 1
A31: 30 | B31: Malang | C31: Tidak | D31: Sales Area (Infinix Indonesia) | E31: Excel | F31: Cari Kerja, Upskill, Networking, Switch Career | G31: LinkedIn | H31: =IFERROR(VLOOKUP(TRIM(IF(ISNUMBER(FIND(",", B31)),LEFT(B31,FIND(",",B31)-1),B31)),master!A:B,2,FALSE),"Belum ada mapping") -> Jawa Timur | I31: =IFERROR(__xludf.DUMMYFUNCTION("IF(REGEXMATCH(F31,""Cari Kerja""),1,0)"),1.0) -> 1
A32: 31 | B32: Bekasi | C32: Ya | D32: Politeknik Takumi | E32: Excel, Power BI, Looker Studio, Tableau | F32: Cari Kerja, Upskill, Networking, Switch Career | G32: LinkedIn | H32: =IFERROR(VLOOKUP(TRIM(IF(ISNUMBER(FIND(",", B32)),LEFT(B32,FIND(",",B32)-1),B32)),master!A:B,2,FALSE),"Belum ada mapping") -> Jawa Barat | I32: =IFERROR(__xludf.DUMMYFUNCTION("IF(REGEXMATCH(F32,""Cari Kerja""),1,0)"),1.0) -> 1
A33: 32 | B33: Jakarta | C33: Tidak | D33: Phl di RS Bhayangkara Tk I Pusdokkes Polri | E33: Excel, SQL, Python, Databases | F33: Cari Kerja, Upskill, Networking, Switch Career | G33: Teman | H33: =IFERROR(VLOOKUP(TRIM(IF(ISNUMBER(FIND(",", B33)),LEFT(B33,FIND(",",B33)-1),B33)),master!A:B,2,FALSE),"Belum ada mapping") -> Jakarta | I33: =IFERROR(__xludf.DUMMYFUNCTION("IF(REGEXMATCH(F33,""Cari Kerja""),1,0)"),1.0) -> 1
A34: 33 | B34: Sumatera selatan | C34: Tidak | D34: PT Satria Mayangkara Service | E34: Excel, Looker Studio, Databases | F34: Upskill | G34: LinkedIn | H34: =IFERROR(VLOOKUP(TRIM(IF(ISNUMBER(FIND(",", B34)),LEFT(B34,FIND(",",B34)-1),B34)),master!A:B,2,FALSE),"Belum ada mapping") -> Sumatera Selatan | I34: =IFERROR(__xludf.DUMMYFUNCTION("IF(REGEXMATCH(F34,""Cari Kerja""),1,0)"),0.0) -> 0
A35: 34 | B35: Bandung | C35: Tidak | D35: Data operations | E35: Excel, SQL, Python, Databases, Tableau | F35: Upskill, Networking | G35: Teman | H35: =IFERROR(VLOOKUP(TRIM(IF(ISNUMBER(FIND(",", B35)),LEFT(B35,FIND(",",B35)-1),B35)),master!A:B,2,FALSE),"Belum ada mapping") -> Jawa Barat | I35: =IFERROR(__xludf.DUMMYFUNCTION("IF(REGEXMATCH(F35,""Cari Kerja""),1,0)"),0.0) -> 0
A36: 35 | B36: Surabaya | C36: Tidak | D36: Admin support - PT Garis Pertama Solusi | E36: SQL, Python, Power BI, Looker Studio | F36: Cari Kerja, Upskill, Networking | G36: LinkedIn | H36: =IFERROR(VLOOKUP(TRIM(IF(ISNUMBER(FIND(",", B36)),LEFT(B36,FIND(",",B36)-1),B36)),master!A:B,2,FALSE),"Belum ada mapping") -> Jawa Timur | I36: =IFERROR(__xludf.DUMMYFUNCTION("IF(REGEXMATCH(F36,""Cari Kerja""),1,0)"),1.0) -> 1
A37: 36 | B37: Jakarta | C37: Tidak | D37: Pegawai Swasta - Corporate Banking Relationship Manager | E37: Excel, SQL, Python, Power BI, Databases, Tableau | F37: Cari Kerja, Upskill, Networking, Switch Career | G37: Instagram | H37: =IFERROR(VLOOKUP(TRIM(IF(ISNUMBER(FIND(",", B37)),LEFT(B37,FIND(",",B37)-1),B37)),master!A:B,2,FALSE),"Belum ada mapping") -> Jakarta | I37: =IFERROR(__xludf.DUMMYFUNCTION("IF(REGEXMATCH(F37,""Cari Kerja""),1,0)"),1.0) -> 1
A38: 37 | B38: Medan | C38: Ya | D38: Fresh graduate | E38: Excel, Python, Databases | F38: Cari Kerja, Upskill, Networking, Switch Career | G38: Instagram | H38: =IFERROR(VLOOKUP(TRIM(IF(ISNUMBER(FIND(",", B38)),LEFT(B38,FIND(",",B38)-1),B38)),master!A:B,2,FALSE),"Belum ada mapping") -> Sumatera Utara | I38: =IFERROR(__xludf.DUMMYFUNCTION("IF(REGEXMATCH(F38,""Cari Kerja""),1,0)"),1.0) -> 1
A39: 38 | B39: Tangerang Selatan | C39: Ya | D39: UIN Jakarta | E39: Excel, SQL, Python, Power BI, Looker Studio, Databases, Tableau | F39: Cari Kerja, Upskill, Networking | G39: LinkedIn | H39: =IFERROR(VLOOKUP(TRIM(IF(ISNUMBER(FIND(",", B39)),LEFT(B39,FIND(",",B39)-1),B39)),master!A:B,2,FALSE),"Belum ada mapping") -> Banten | I39: =IFERROR(__xludf.DUMMYFUNCTION("IF(REGEXMATCH(F39,""Cari Kerja""),1,0)"),1.0) -> 1
A40: 39 | B40: tangerang selatan | C40: Tidak | D40: finance | E40: SQL, Python, Power BI, Looker Studio, Databases, Tableau | F40: Upskill | G40: LinkedIn | H40: =IFERROR(VLOOKUP(TRIM(IF(ISNUMBER(FIND(",", B40)),LEFT(B40,FIND(",",B40)-1),B40)),master!A:B,2,FALSE),"Belum ada mapping") -> Banten | I40: =IFERROR(__xludf.DUMMYFUNCTION("IF(REGEXMATCH(F40,""Cari Kerja""),1,0)"),0.0) -> 0
A41: 40 | B41: Makassar | C41: Tidak | D41: Jobseeker | E41: Excel, SQL, Python, Power BI, Looker Studio, Databases, Tableau | F41: Cari Kerja, Upskill, Networking, Switch Career | G41: LinkedIn | H41: =IFERROR(VLOOKUP(TRIM(IF(ISNUMBER(FIND(",", B41)),LEFT(B41,FIND(",",B41)-1),B41)),master!A:B,2,FALSE),"Belum ada mapping") -> Sulawesi Selatan | I41: =IFERROR(__xludf.DUMMYFUNCTION("IF(REGEXMATCH(F41,""Cari Kerja""),1,0)"),1.0) -> 1
A42: 41 | B42: Serang | C42: Tidak | D42: - | E42: Excel, SQL, Power BI, | F42: Cari Kerja, Upskill, Switch Career | G42: LinkedIn | H42: =IFERROR(VLOOKUP(TRIM(IF(ISNUMBER(FIND(",", B42)),LEFT(B42,FIND(",",B42)-1),B42)),master!A:B,2,FALSE),"Belum ada mapping") -> Banten | I42: =IFERROR(__xludf.DUMMYFUNCTION("IF(REGEXMATCH(F42,""Cari Kerja""),1,0)"),1.0) -> 1
A43: 42 | B43: Tangerang Selatan | C43: Ya | D43: mahasiswa | E43: Excel, SQL, Python, Power BI, Looker Studio, Databases, Tableau | F43: Cari Kerja, Upskill, Networking | G43: LinkedIn | H43: =IFERROR(VLOOKUP(TRIM(IF(ISNUMBER(FIND(",", B43)),LEFT(B43,FIND(",",B43)-1),B43)),master!A:B,2,FALSE),"Belum ada mapping") -> Banten | I43: =IFERROR(__xludf.DUMMYFUNCTION("IF(REGEXMATCH(F43,""Cari Kerja""),1,0)"),1.0) -> 1
A44: 43 | B44: Malang | C44: Tidak | D44: Business Intelligence | E44: SQL, Python, Power BI, Databases, Tableau | F44: Upskill, Networking, Switch Career | G44: LinkedIn | H44: =IFERROR(VLOOKUP(TRIM(IF(ISNUMBER(FIND(",", B44)),LEFT(B44,FIND(",",B44)-1),B44)),master!A:B,2,FALSE),"Belum ada mapping") -> Jawa Timur | I44: =IFERROR(__xludf.DUMMYFUNCTION("IF(REGEXMATCH(F44,""Cari Kerja""),1,0)"),0.0) -> 0
A45: 44 | B45: Jambi | C45: Tidak | D45: Data Management PT Wirakarya Sakti | E45: Excel, SQL, Python, Power BI, Looker Studio, Databases, Tableau | F45: Upskill, Networking, Switch Career | G45: LinkedIn | H45: =IFERROR(VLOOKUP(TRIM(IF(ISNUMBER(FIND(",", B45)),LEFT(B45,FIND(",",B45)-1),B45)),master!A:B,2,FALSE),"Belum ada mapping") -> Jambi | I45: =IFERROR(__xludf.DUMMYFUNCTION("IF(REGEXMATCH(F45,""Cari Kerja""),1,0)"),0.0) -> 0
A46: 45 | B46: Bekasi | C46: Ya | D46: Ojek Online | E46: Excel, SQL, Python, Power BI, Looker Studio, Databases, Tableau | F46: Cari Kerja, Upskill, Networking | G46: LinkedIn | H46: =IFERROR(VLOOKUP(TRIM(IF(ISNUMBER(FIND(",", B46)),LEFT(B46,FIND(",",B46)-1),B46)),master!A:B,2,FALSE),"Belum ada mapping") -> Jawa Barat | I46: =IFERROR(__xludf.DUMMYFUNCTION("IF(REGEXMATCH(F46,""Cari Kerja""),1,0)"),1.0) -> 1
A47: 46 | B47: Gresik | C47: Tidak | D47: Cpns kemenag | E47: SQL, Python, Power BI, Looker Studio, Databases, Tableau, Data analyst spesifik dunia sosial | F47: Upskill, Networking, Switch Career | G47: Teman | H47: =IFERROR(VLOOKUP(TRIM(IF(ISNUMBER(FIND(",", B47)),LEFT(B47,FIND(",",B47)-1),B47)),master!A:B,2,FALSE),"Belum ada mapping") -> Jawa Timur | I47: =IFERROR(__xludf.DUMMYFUNCTION("IF(REGEXMATCH(F47,""Cari Kerja""),1,0)"),0.0) -> 0
A48: 47 | B48: Jakarta | C48: Ya | D48: - | E48: Excel, SQL, Python, Power BI, Looker Studio, Databases, Tableau | F48: Cari Kerja, Upskill, Networking, Switch Career | G48: LinkedIn | H48: =IFERROR(VLOOKUP(TRIM(IF(ISNUMBER(FIND(",", B48)),LEFT(B48,FIND(",",B48)-1),B48)),master!A:B,2,FALSE),"Belum ada mapping") -> Jakarta | I48: =IFERROR(__xludf.DUMMYFUNCTION("IF(REGEXMATCH(F48,""Cari Kerja""),1,0)"),1.0) -> 1
A49: 48 | B49: Purwokerto | C49: Ya | D49: Mahasiswa | E49: Looker Studio, Tableau | F49: Cari Kerja, Upskill, Networking | G49: LinkedIn | H49: =IFERROR(VLOOKUP(TRIM(IF(ISNUMBER(FIND(",", B49)),LEFT(B49,FIND(",",B49)-1),B49)),master!A:B,2,FALSE),"Belum ada mapping") -> Jawa Tengah | I49: =IFERROR(__xludf.DUMMYFUNCTION("IF(REGEXMATCH(F49,""Cari Kerja""),1,0)"),1.0) -> 1
A50: 49 | B50: Malang | C50: Ya | D50: Mahasiswa dan Freelance | E50: SQL, Python, Power BI, Looker Studio | F50: Networking | G50: LinkedIn | H50: =IFERROR(VLOOKUP(TRIM(IF(ISNUMBER(FIND(",", B50)),LEFT(B50,FIND(",",B50)-1),B50)),master!A:B,2,FALSE),"Belum ada mapping") -> Jawa Timur | I50: =IFERROR(__xludf.DUMMYFUNCTION("IF(REGEXMATCH(F50,""Cari Kerja""),1,0)"),0.0) -> 0
A51: 50 | B51: Mojokerto | C51: Ya | D51: Data Analyst Support - Statsme | E51: SQL, Python, Databases | F51: Upskill, Networking | G51: Teman | H51: =IFERROR(VLOOKUP(TRIM(IF(ISNUMBER(FIND(",", B51)),LEFT(B51,FIND(",",B51)-1),B51)),master!A:B,2,FALSE),"Belum ada mapping") -> Jawa Timur | I51: =IFERROR(__xludf.DUMMYFUNCTION("IF(REGEXMATCH(F51,""Cari Kerja""),1,0)"),0.0) -> 0
A52: 51 | B52: Tangerang | C52: Ya | D52: Fresh Graduate | E52: Excel, SQL, Python, Power BI, Looker Studio, Databases, Tableau | F52: Cari Kerja, Upskill | G52: LinkedIn | H52: =IFERROR(VLOOKUP(TRIM(IF(ISNUMBER(FIND(",", B52)),LEFT(B52,FIND(",",B52)-1),B52)),master!A:B,2,FALSE),"Belum ada mapping") -> Banten | I52: =IFERROR(__xludf.DUMMYFUNCTION("IF(REGEXMATCH(F52,""Cari Kerja""),1,0)"),1.0) -> 1
A53: 52 | B53: Tangerang | C53: Ya | D53: PT Zyrexindo Mandiri Buana Tbk | E53: Excel, SQL, Python, Power BI, Looker Studio, Databases, Tableau, Semua Tools Data Analyst | F53: Cari Kerja, Upskill, Networking | G53: LinkedIn | H53: =IFERROR(VLOOKUP(TRIM(IF(ISNUMBER(FIND(",", B53)),LEFT(B53,FIND(",",B53)-1),B53)),master!A:B,2,FALSE),"Belum ada mapping") -> Banten | I53: =IFERROR(__xludf.DUMMYFUNCTION("IF(REGEXMATCH(F53,""Cari Kerja""),1,0)"),1.0) -> 1
A54: 53 | B54: Tangerang | C54: Tidak | D54: karyawan swasta | E54: Excel, SQL, Python, Power BI, Looker Studio, Databases, Tableau | F54: Cari Kerja, Upskill, Networking | G54: LinkedIn | H54: =IFERROR(VLOOKUP(TRIM(IF(ISNUMBER(FIND(",", B54)),LEFT(B54,FIND(",",B54)-1),B54)),master!A:B,2,FALSE),"Belum ada mapping") -> Banten | I54: =IFERROR(__xludf.DUMMYFUNCTION("IF(REGEXMATCH(F54,""Cari Kerja""),1,0)"),1.0) -> 1
A55: 54 | B55: Jakarta | C55: Ya | D55: - | E55: Looker Studio, Databases, Tableau | F55: Upskill, Networking, Switch Career | G55: LinkedIn | H55: =IFERROR(VLOOKUP(TRIM(IF(ISNUMBER(FIND(",", B55)),LEFT(B55,FIND(",",B55)-1),B55)),master!A:B,2,FALSE),"Belum ada mapping") -> Jakarta | I55: =IFERROR(__xludf.DUMMYFUNCTION("IF(REGEXMATCH(F55,""Cari Kerja""),1,0)"),0.0) -> 0
A56: 55 | B56: Palangkaraya Kalimantan Tengah | C56: Tidak | D56: PT. Gojek Tokopedia | E56: SQL | F56: Upskill, Networking, Switch Career | G56: LinkedIn | H56: =IFERROR(VLOOKUP(TRIM(IF(ISNUMBER(FIND(",", B56)),LEFT(B56,FIND(",",B56)-1),B56)),master!A:B,2,FALSE),"Belum ada mapping") -> Kalimatan Tengah | I56: =IFERROR(__xludf.DUMMYFUNCTION("IF(REGEXMATCH(F56,""Cari Kerja""),1,0)"),0.0) -> 0
A57: 56 | B57: Jawa Tengah | C57: Ya | D57: Mahasiswa | E57: Excel, SQL, Python, Tableau | F57: Cari Kerja | G57: Teman | H57: =IFERROR(VLOOKUP(TRIM(IF(ISNUMBER(FIND(",", B57)),LEFT(B57,FIND(",",B57)-1),B57)),master!A:B,2,FALSE),"Belum ada mapping") -> Jawa Tengah | I57: =IFERROR(__xludf.DUMMYFUNCTION("IF(REGEXMATCH(F57,""Cari Kerja""),1,0)"),1.0) -> 1
A58: 57 | B58: Jember | C58: Ya | D58: Mahasiswa semester 2 | E58: Excel, SQL, Python, Databases, Tableau | F58: Cari Kerja, Upskill, Networking | G58: LinkedIn | H58: =IFERROR(VLOOKUP(TRIM(IF(ISNUMBER(FIND(",", B58)),LEFT(B58,FIND(",",B58)-1),B58)),master!A:B,2,FALSE),"Belum ada mapping") -> Jawa Timur | I58: =IFERROR(__xludf.DUMMYFUNCTION("IF(REGEXMATCH(F58,""Cari Kerja""),1,0)"),1.0) -> 1
A59: 58 | B59: Jakarta | C59: Tidak | D59: Business Data Analis | E59: Python, Power BI, Looker Studio, Databases, Tableau | F59: Upskill | G59: LinkedIn | H59: =IFERROR(VLOOKUP(TRIM(IF(ISNUMBER(FIND(",", B59)),LEFT(B59,FIND(",",B59)-1),B59)),master!A:B,2,FALSE),"Belum ada mapping") -> Jakarta | I59: =IFERROR(__xludf.DUMMYFUNCTION("IF(REGEXMATCH(F59,""Cari Kerja""),1,0)"),0.0) -> 0
A60: 59 | B60: Bekasi | C60: Tidak | D60: Coordinator Application Development - PT Multi Kontrol Nusantara | E60: ETL | F60: Cari Kerja, Upskill, Networking | G60: LinkedIn | H60: =IFERROR(VLOOKUP(TRIM(IF(ISNUMBER(FIND(",", B60)),LEFT(B60,FIND(",",B60)-1),B60)),master!A:B,2,FALSE),"Belum ada mapping") -> Jawa Barat | I60: =IFERROR(__xludf.DUMMYFUNCTION("IF(REGEXMATCH(F60,""Cari Kerja""),1,0)"),1.0) -> 1
A61: 60 | B61: Jakarta | C61: Tidak | D61: Data Enginner & Telkomsel | E61: Hadoop, Hive Server | F61: Upskill, Networking | G61: LinkedIn | H61: =IFERROR(VLOOKUP(TRIM(IF(ISNUMBER(FIND(",", B61)),LEFT(B61,FIND(",",B61)-1),B61)),master!A:B,2,FALSE),"Belum ada mapping") -> Jakarta | I61: =IFERROR(__xludf.DUMMYFUNCTION("IF(REGEXMATCH(F61,""Cari Kerja""),1,0)"),0.0) -> 0
A62: 61 | B62: Jakarta Utara | C62: Tidak | D62: Data Engineer & Automation reporting | E62: Tableau | F62: Networking | G62: LinkedIn | H62: =IFERROR(VLOOKUP(TRIM(IF(ISNUMBER(FIND(",", B62)),LEFT(B62,FIND(",",B62)-1),B62)),master!A:B,2,FALSE),"Belum ada mapping") -> Jakarta | I62: =IFERROR(__xludf.DUMMYFUNCTION("IF(REGEXMATCH(F62,""Cari Kerja""),1,0)"),0.0) -> 0
A63: 62 | B63: surabaya | C63: Tidak | D63: data analyst pt ratna asia | E63: SQL, Databases, Tableau | F63: Upskill | G63: LinkedIn | H63: =IFERROR(VLOOKUP(TRIM(IF(ISNUMBER(FIND(",", B63)),LEFT(B63,FIND(",",B63)-1),B63)),master!A:B,2,FALSE),"Belum ada mapping") -> Jawa Timur | I63: =IFERROR(__xludf.DUMMYFUNCTION("IF(REGEXMATCH(F63,""Cari Kerja""),1,0)"),0.0) -> 0
A64: 63 | B64: Jakarta | C64: Tidak | D64: Inventory Management & Cipta Kridatama | E64: Excel, SQL, Power BI, Databases, Tableau | F64: Upskill, Networking | G64: LinkedIn | H64: =IFERROR(VLOOKUP(TRIM(IF(ISNUMBER(FIND(",", B64)),LEFT(B64,FIND(",",B64)-1),B64)),master!A:B,2,FALSE),"Belum ada mapping") -> Jakarta | I64: =IFERROR(__xludf.DUMMYFUNCTION("IF(REGEXMATCH(F64,""Cari Kerja""),1,0)"),0.0) -> 0
A65: 64 | B65: Surabaya | C65: Ya | D65: Universitas Teknologi Surabaya | E65: Excel, SQL, Python, Looker Studio, Databases | F65: Cari Kerja, Upskill, Networking, Switch Career | G65: Teman | H65: =IFERROR(VLOOKUP(TRIM(IF(ISNUMBER(FIND(",", B65)),LEFT(B65,FIND(",",B65)-1),B65)),master!A:B,2,FALSE),"Belum ada mapping") -> Jawa Timur | I65: =IFERROR(__xludf.DUMMYFUNCTION("IF(REGEXMATCH(F65,""Cari Kerja""),1,0)"),1.0) -> 1
A66: 65 | B66: Tangerang | C66: Ya | D66: Chemical Researchwr | E66: Python, Power BI, Looker Studio, Databases | F66: Cari Kerja, Upskill, Networking, Switch Career | G66: LinkedIn | H66: =IFERROR(VLOOKUP(TRIM(IF(ISNUMBER(FIND(",", B66)),LEFT(B66,FIND(",",B66)-1),B66)),master!A:B,2,FALSE),"Belum ada mapping") -> Banten | I66: =IFERROR(__xludf.DUMMYFUNCTION("IF(REGEXMATCH(F66,""Cari Kerja""),1,0)"),1.0) -> 1
A67: 66 | B67: Sidoarjo | C67: Ya | D67: PT. Tiga Berlian Mandiri | E67: SQL, Python, Power BI, Looker Studio, Databases, Tableau | F67: Cari Kerja, Upskill, Networking | G67: LinkedIn | H67: =IFERROR(VLOOKUP(TRIM(IF(ISNUMBER(FIND(",", B67)),LEFT(B67,FIND(",",B67)-1),B67)),master!A:B,2,FALSE),"Belum ada mapping") -> Jawa Timur | I67: =IFERROR(__xludf.DUMMYFUNCTION("IF(REGEXMATCH(F67,""Cari Kerja""),1,0)"),1.0) -> 1
A68: 67 | B68: Surabaya | C68: Ya | D68: Universitas Negeri Surabaya | E68: Excel, SQL, Python, Power BI, Looker Studio, Databases, Tableau | F68: Cari Kerja, Upskill, Networking | G68: LinkedIn | H68: =IFERROR(VLOOKUP(TRIM(IF(ISNUMBER(FIND(",", B68)),LEFT(B68,FIND(",",B68)-1),B68)),master!A:B,2,FALSE),"Belum ada mapping") -> Jawa Timur | I68: =IFERROR(__xludf.DUMMYFUNCTION("IF(REGEXMATCH(F68,""Cari Kerja""),1,0)"),1.0) -> 1
A69: 68 | B69: Jakarta Selatan | C69: Tidak | D69: Data Engineer | E69: Excel, SQL, Python, Databases | F69: Upskill, Networking | G69: LinkedIn | H69: =IFERROR(VLOOKUP(TRIM(IF(ISNUMBER(FIND(",", B69)),LEFT(B69,FIND(",",B69)-1),B69)),master!A:B,2,FALSE),"Belum ada mapping") -> Jakarta | I69: =IFERROR(__xludf.DUMMYFUNCTION("IF(REGEXMATCH(F69,""Cari Kerja""),1,0)"),0.0) -> 0
A70: 69 | B70: Bandung | C70: Tidak | D70: Data Analyst | E70: SQL, Python, Power BI, Databases | F70: Upskill, Networking | G70: LinkedIn | H70: =IFERROR(VLOOKUP(TRIM(IF(ISNUMBER(FIND(",", B70)),LEFT(B70,FIND(",",B70)-1),B70)),master!A:B,2,FALSE),"Belum ada mapping") -> Jawa Barat | I70: =IFERROR(__xludf.DUMMYFUNCTION("IF(REGEXMATCH(F70,""Cari Kerja""),1,0)"),0.0) -> 0
A71: 70 | B71: Jakarta | C71: Ya | D71: Mahasiswa | E71: Excel, SQL, Python, Looker Studio, Databases | F71: Upskill, Networking | G71: LinkedIn | H71: =IFERROR(VLOOKUP(TRIM(IF(ISNUMBER(FIND(",", B71)),LEFT(B71,FIND(",",B71)-1),B71)),master!A:B,2,FALSE),"Belum ada mapping") -> Jakarta | I71: =IFERROR(__xludf.DUMMYFUNCTION("IF(REGEXMATCH(F71,""Cari Kerja""),1,0)"),0.0) -> 0
A72: 71 | B72: Bekasi | C72: Tidak | D72: Business development & Global Putra Internasional Group | E72: Excel, SQL, Python, Power BI, Databases | F72: Cari Kerja, Upskill, Networking, Switch Career | G72: LinkedIn | H72: =IFERROR(VLOOKUP(TRIM(IF(ISNUMBER(FIND(",", B72)),LEFT(B72,FIND(",",B72)-1),B72)),master!A:B,2,FALSE),"Belum ada mapping") -> Jawa Barat | I72: =IFERROR(__xludf.DUMMYFUNCTION("IF(REGEXMATCH(F72,""Cari Kerja""),1,0)"),1.0) -> 1
A73: 72 | B73: Palangkaraya | C73: Ya | D73: - | E73: Excel, SQL, Python, Databases | F73: Upskill, Networking | G73: Teman | H73: =IFERROR(VLOOKUP(TRIM(IF(ISNUMBER(FIND(",", B73)),LEFT(B73,FIND(",",B73)-1),B73)),master!A:B,2,FALSE),"Belum ada mapping") -> Kalimantan Tengah | I73: =IFERROR(__xludf.DUMMYFUNCTION("IF(REGEXMATCH(F73,""Cari Kerja""),1,0)"),0.0) -> 0
A74: 73 | B74: Balikpapan | C74: Tidak | D74: 0 | E74: Python, Power BI, Looker Studio, Databases | F74: Cari Kerja, Upskill, Networking | G74: LinkedIn | H74: =IFERROR(VLOOKUP(TRIM(IF(ISNUMBER(FIND(",", B74)),LEFT(B74,FIND(",",B74)-1),B74)),master!A:B,2,FALSE),"Belum ada mapping") -> Kalimantan Timur | I74: =IFERROR(__xludf.DUMMYFUNCTION("IF(REGEXMATCH(F74,""Cari Kerja""),1,0)"),1.0) -> 1
A75: 74 | B75: PARINGIN | C75: Tidak | D75: WIRASWASTA | E75: Excel, SQL, Power BI, Databases | F75: Upskill, Networking | G75: LinkedIn | H75: =IFERROR(VLOOKUP(TRIM(IF(ISNUMBER(FIND(",", B75)),LEFT(B75,FIND(",",B75)-1),B75)),master!A:B,2,FALSE),"Belum ada mapping") -> Kalimantan Selatan | I75: =IFERROR(__xludf.DUMMYFUNCTION("IF(REGEXMATCH(F75,""Cari Kerja""),1,0)"),0.0) -> 0
A76: 75 | B76: Medan | C76: Tidak | D76: Pemerintahan | E76: SQL, Looker Studio | F76: Upskill | G76: LinkedIn | H76: =IFERROR(VLOOKUP(TRIM(IF(ISNUMBER(FIND(",", B76)),LEFT(B76,FIND(",",B76)-1),B76)),master!A:B,2,FALSE),"Belum ada mapping") -> Sumatera Utara | I76: =IFERROR(__xludf.DUMMYFUNCTION("IF(REGEXMATCH(F76,""Cari Kerja""),1,0)"),0.0) -> 0
A77: 76 | B77: Jakarta selatan | C77: Ya | D77: - | E77: Excel, SQL, Python, Power BI, Looker Studio, Databases, Tableau | F77: Cari Kerja, Upskill, Networking | G77: Instagram | H77: =IFERROR(VLOOKUP(TRIM(IF(ISNUMBER(FIND(",", B77)),LEFT(B77,FIND(",",B77)-1),B77)),master!A:B,2,FALSE),"Belum ada mapping") -> Jakarta | I77: =IFERROR(__xludf.DUMMYFUNCTION("IF(REGEXMATCH(F77,""Cari Kerja""),1,0)"),1.0) -> 1
A78: 77 | B78: Bulukumba | C78: Tidak | D78: IRT | E78: Excel, SQL, Python, Power BI, Tableau | F78: Cari Kerja | G78: Teman | H78: =IFERROR(VLOOKUP(TRIM(IF(ISNUMBER(FIND(",", B78)),LEFT(B78,FIND(",",B78)-1),B78)),master!A:B,2,FALSE),"Belum ada mapping") -> Sulawesi Selatan | I78: =IFERROR(__xludf.DUMMYFUNCTION("IF(REGEXMATCH(F78,""Cari Kerja""),1,0)"),1.0) -> 1
A79: 78 | B79: Tulungagung | C79: Ya | D79: SCO JNE | E79: Excel, SQL, Python, Power BI, Looker Studio, Databases, Tableau | F79: Cari Kerja, Upskill, Networking | G79: LinkedIn | H79: =IFERROR(VLOOKUP(TRIM(IF(ISNUMBER(FIND(",", B79)),LEFT(B79,FIND(",",B79)-1),B79)),master!A:B,2,FALSE),"Belum ada mapping") -> Jawa Tengah | I79: =IFERROR(__xludf.DUMMYFUNCTION("IF(REGEXMATCH(F79,""Cari Kerja""),1,0)"),1.0) -> 1
A80: 79 | B80: Yogyakarta | C80: Ya | D80: Wiraswasta | E80: Excel, SQL, Python, Power BI, Databases, Tableau | F80: Cari Kerja, Upskill, Networking | G80: LinkedIn | H80: =IFERROR(VLOOKUP(TRIM(IF(ISNUMBER(FIND(",", B80)),LEFT(B80,FIND(",",B80)-1),B80)),master!A:B,2,FALSE),"Belum ada mapping") -> DI Yogyakarta | I80: =IFERROR(__xludf.DUMMYFUNCTION("IF(REGEXMATCH(F80,""Cari Kerja""),1,0)"),1.0) -> 1
A81: 80 | B81: Depok | C81: Tidak | D81: Project Management & NTi | E81: SQL, Python, Power BI, Looker Studio, Databases, Tableau | F81: Cari Kerja, Upskill, Networking | G81: LinkedIn | H81: =IFERROR(VLOOKUP(TRIM(IF(ISNUMBER(FIND(",", B81)),LEFT(B81,FIND(",",B81)-1),B81)),master!A:B,2,FALSE),"Belum ada mapping") -> Jawa Barat | I81: =IFERROR(__xludf.DUMMYFUNCTION("IF(REGEXMATCH(F81,""Cari Kerja""),1,0)"),1.0) -> 1
A82: 81 | B82: Tanjung Enim, Sumatera Selatan | C82: Tidak | D82: Karyaean Swasta | E82: Excel, SQL, Python, Power BI, Looker Studio, Databases, Tableau | F82: Cari Kerja, Upskill, Networking, Switch Career | G82: Instagram | H82: =IFERROR(VLOOKUP(TRIM(IF(ISNUMBER(FIND(",", B82)),LEFT(B82,FIND(",",B82)-1),B82)),master!A:B,2,FALSE),"Belum ada mapping") -> Sumatera Selatan | I82: =IFERROR(__xludf.DUMMYFUNCTION("IF(REGEXMATCH(F82,""Cari Kerja""),1,0)"),1.0) -> 1
A83: 82 | B83: sangatta | C83: Tidak | D83: maintenance instruktur , februari pindah jabatan menjadi maintenance planner | E83: Excel, Python, Power BI, Databases | F83: Upskill | G83: LinkedIn | H83: =IFERROR(VLOOKUP(TRIM(IF(ISNUMBER(FIND(",", B83)),LEFT(B83,FIND(",",B83)-1),B83)),master!A:B,2,FALSE),"Belum ada mapping") -> Kalimantan Timur | I83: =IFERROR(__xludf.DUMMYFUNCTION("IF(REGEXMATCH(F83,""Cari Kerja""),1,0)"),0.0) -> 0
A84: 83 | B84: Malang | C84: Ya | D84: Mahasiswa | E84: Excel, SQL, Python, Power BI, Databases | F84: Cari Kerja, Upskill | G84: LinkedIn | H84: =IFERROR(VLOOKUP(TRIM(IF(ISNUMBER(FIND(",", B84)),LEFT(B84,FIND(",",B84)-1),B84)),master!A:B,2,FALSE),"Belum ada mapping") -> Jawa Timur | I84: =IFERROR(__xludf.DUMMYFUNCTION("IF(REGEXMATCH(F84,""Cari Kerja""),1,0)"),1.0) -> 1
A85: 84 | B85: Jakarta Timur | C85: Ya | D85: Belum bekerja | E85: Excel, SQL, Python | F85: Cari Kerja, Upskill | G85: LinkedIn | H85: =IFERROR(VLOOKUP(TRIM(IF(ISNUMBER(FIND(",", B85)),LEFT(B85,FIND(",",B85)-1),B85)),master!A:B,2,FALSE),"Belum ada mapping") -> Jakarta | I85: =IFERROR(__xludf.DUMMYFUNCTION("IF(REGEXMATCH(F85,""Cari Kerja""),1,0)"),1.0) -> 1
A86: 85 | B86: Surakarta | C86: Ya | D86: Mahasiswa Universitas Sebelas Maret | E86: Excel, SQL, Python, Power BI, Tableau | F86: Upskill, Networking | G86: LinkedIn | H86: =IFERROR(VLOOKUP(TRIM(IF(ISNUMBER(FIND(",", B86)),LEFT(B86,FIND(",",B86)-1),B86)),master!A:B,2,FALSE),"Belum ada mapping") -> Jawa Tengah | I86: =IFERROR(__xludf.DUMMYFUNCTION("IF(REGEXMATCH(F86,""Cari Kerja""),1,0)"),0.0) -> 0
A87: 86 | B87: Jakarta | C87: Tidak | D87: Logistik | E87: Excel, Looker Studio, Databases | F87: Switch Career | G87: Instagram | H87: =IFERROR(VLOOKUP(TRIM(IF(ISNUMBER(FIND(",", B87)),LEFT(B87,FIND(",",B87)-1),B87)),master!A:B,2,FALSE),"Belum ada mapping") -> Jakarta | I87: =IFERROR(__xludf.DUMMYFUNCTION("IF(REGEXMATCH(F87,""Cari Kerja""),1,0)"),0.0) -> 0
A88: 87 | B88: Palembang | C88: Tidak | D88: Jobseeker | E88: SQL, Python, Power BI, Looker Studio, Tableau | F88: Cari Kerja, Networking, Switch Career | G88: Instagram | H88: =IFERROR(VLOOKUP(TRIM(IF(ISNUMBER(FIND(",", B88)),LEFT(B88,FIND(",",B88)-1),B88)),master!A:B,2,FALSE),"Belum ada mapping") -> Sumatera Selatan | I88: =IFERROR(__xludf.DUMMYFUNCTION("IF(REGEXMATCH(F88,""Cari Kerja""),1,0)"),1.0) -> 1
A89: 88 | B89: Lampung | C89: Ya | D89: - | E89: Excel, SQL, Python, Power BI, Looker Studio, Databases, Tableau | F89: Cari Kerja, Upskill, Networking | G89: LinkedIn | H89: =IFERROR(VLOOKUP(TRIM(IF(ISNUMBER(FIND(",", B89)),LEFT(B89,FIND(",",B89)-1),B89)),master!A:B,2,FALSE),"Belum ada mapping") -> Lampung | I89: =IFERROR(__xludf.DUMMYFUNCTION("IF(REGEXMATCH(F89,""Cari Kerja""),1,0)"),1.0) -> 1
A90: 89 | B90: DKI Jakarta | C90: Ya | D90: Technical Support - PLN ICONPLUS | E90: SQL, Python, Power BI, Tableau | F90: Upskill, Networking, Switch Career | G90: LinkedIn | H90: =IFERROR(VLOOKUP(TRIM(IF(ISNUMBER(FIND(",", B90)),LEFT(B90,FIND(",",B90)-1),B90)),master!A:B,2,FALSE),"Belum ada mapping") -> Jakarta | I90: =IFERROR(__xludf.DUMMYFUNCTION("IF(REGEXMATCH(F90,""Cari Kerja""),1,0)"),0.0) -> 0
A91: 90 | B91: Kudus | C91: Tidak | D91: PT HWI | E91: Excel, SQL, Python, Power BI, Looker Studio, Databases, Tableau | F91: Cari Kerja, Upskill, Networking, Switch Career | G91: LinkedIn | H91: =IFERROR(VLOOKUP(TRIM(IF(ISNUMBER(FIND(",", B91)),LEFT(B91,FIND(",",B91)-1),B91)),master!A:B,2,FALSE),"Belum ada mapping") -> Jawa Tengah | I91: =IFERROR(__xludf.DUMMYFUNCTION("IF(REGEXMATCH(F91,""Cari Kerja""),1,0)"),1.0) -> 1
A92: 91 | B92: Malang, Jawa Timur | C92: Ya | D92: Mahasiswa di UIN Maulana Malik Ibrahim Malang | E92: Excel, SQL, Python, Power BI, Looker Studio, Databases, Tableau | F92: Cari Kerja, Upskill, Networking | G92: Teman | H92: =IFERROR(VLOOKUP(TRIM(IF(ISNUMBER(FIND(",", B92)),LEFT(B92,FIND(",",B92)-1),B92)),master!A:B,2,FALSE),"Belum ada mapping") -> Jawa Timur | I92: =IFERROR(__xludf.DUMMYFUNCTION("IF(REGEXMATCH(F92,""Cari Kerja""),1,0)"),1.0) -> 1
A93: 92 | B93: Jakarta Selatan | C93: Ya | D93: Magang di Kementrian Pertanian | E93: Excel, SQL, Python, Power BI, Looker Studio, Databases, Tableau | F93: Cari Kerja, Upskill | G93: LinkedIn | H93: =IFERROR(VLOOKUP(TRIM(IF(ISNUMBER(FIND(",", B93)),LEFT(B93,FIND(",",B93)-1),B93)),master!A:B,2,FALSE),"Belum ada mapping") -> Jakarta | I93: =IFERROR(__xludf.DUMMYFUNCTION("IF(REGEXMATCH(F93,""Cari Kerja""),1,0)"),1.0) -> 1
A94: 93 | B94: Tangerang | C94: Ya | D94: Supply Chain Management Officer | E94: Excel, Python, Power BI, Databases | F94: Upskill, Networking | G94: Instagram | H94: =IFERROR(VLOOKUP(TRIM(IF(ISNUMBER(FIND(",", B94)),LEFT(B94,FIND(",",B94)-1),B94)),master!A:B,2,FALSE),"Belum ada mapping") -> Banten | I94: =IFERROR(__xludf.DUMMYFUNCTION("IF(REGEXMATCH(F94,""Cari Kerja""),1,0)"),0.0) -> 0
A95: 94 | B95: Semarang | C95: Ya | D95: Unnisula | E95: Excel, SQL, Python, Power BI, Looker Studio, Databases, Tableau | F95: Cari Kerja, Upskill, Networking | G95: Teman | H95: =IFERROR(VLOOKUP(TRIM(IF(ISNUMBER(FIND(",", B95)),LEFT(B95,FIND(",",B95)-1),B95)),master!A:B,2,FALSE),"Belum ada mapping") -> Jawa Tengah | I95: =IFERROR(__xludf.DUMMYFUNCTION("IF(REGEXMATCH(F95,""Cari Kerja""),1,0)"),1.0) -> 1
A96: 95 | B96: Banyumas | C96: Ya | D96: Mahasiswa | E96: Excel, SQL, Python, Power BI, Looker Studio, Databases, Tableau | F96: Cari Kerja, Upskill, Networking | G96: LinkedIn | H96: =IFERROR(VLOOKUP(TRIM(IF(ISNUMBER(FIND(",", B96)),LEFT(B96,FIND(",",B96)-1),B96)),master!A:B,2,FALSE),"Belum ada mapping") -> Jawa Tengah | I96: =IFERROR(__xludf.DUMMYFUNCTION("IF(REGEXMATCH(F96,""Cari Kerja""),1,0)"),1.0) -> 1
A97: 96 | B97: Bengkulu | C97: Tidak | D97: - | E97: Excel, SQL, Python | F97: Upskill, Switch Career | G97: LinkedIn | H97: =IFERROR(VLOOKUP(TRIM(IF(ISNUMBER(FIND(",", B97)),LEFT(B97,FIND(",",B97)-1),B97)),master!A:B,2,FALSE),"Belum ada mapping") -> Bengkulu | I97: =IFERROR(__xludf.DUMMYFUNCTION("IF(REGEXMATCH(F97,""Cari Kerja""),1,0)"),0.0) -> 0
A98: 97 | B98: Tangerang | C98: Tidak | D98: Accounting Staff | E98: Excel, SQL, Python, Looker Studio | F98: Upskill, Switch Career | G98: LinkedIn | H98: =IFERROR(VLOOKUP(TRIM(IF(ISNUMBER(FIND(",", B98)),LEFT(B98,FIND(",",B98)-1),B98)),master!A:B,2,FALSE),"Belum ada mapping") -> Banten | I98: =IFERROR(__xludf.DUMMYFUNCTION("IF(REGEXMATCH(F98,""Cari Kerja""),1,0)"),0.0) -> 0
A99: 98 | B99: Lampung | C99: Ya | D99: Magang - KPPN Liwa | E99: SQL, Python, Power BI, Tableau | F99: Cari Kerja, Upskill | G99: LinkedIn | H99: =IFERROR(VLOOKUP(TRIM(IF(ISNUMBER(FIND(",", B99)),LEFT(B99,FIND(",",B99)-1),B99)),master!A:B,2,FALSE),"Belum ada mapping") -> Lampung | I99: =IFERROR(__xludf.DUMMYFUNCTION("IF(REGEXMATCH(F99,""Cari Kerja""),1,0)"),1.0) -> 1
A100: 99 | B100: Batam | C100: Ya | D100: - | E100: Excel, SQL, Python, Power BI, Tableau | F100: Cari Kerja, Networking | G100: Instagram | H100: =IFERROR(VLOOKUP(TRIM(IF(ISNUMBER(FIND(",", B100)),LEFT(B100,FIND(",",B100)-1),B100)),master!A:B,2,FALSE),"Belum ada mapping") -> Riau | I100: =IFERROR(__xludf.DUMMYFUNCTION("IF(REGEXMATCH(F100,""Cari Kerja""),1,0)"),1.0) -> 1
...
